LBDR/ProposedMethod/step4_MutationTesting/MutationTestingSetUp/GoldmineMutationTesting/include/parameters.sv
/********************
* Filename:    parameters.v
* Description: Parameters for Packet FLITS
* $Revision: 21 $
* $Id: parameters.v 21 2015-11-21 10:54:06Z ranga $
* $Date: 2015-11-21 12:54:06 +0200 (Sat, 21 Nov 2015) $
* $Author: ranga $
*********************/

  // defining the flit ID -- One hot encoding
  `define HEADER  3'b001
  `define PAYLOAD 3'b010
  `define TAIL    3'b100

  // Specifying the FIFO parameters
  `define FIFO_DEPTH 'd4               // 4 flits capacity
  `define PTR_SIZE   `FIFO_DEPTH       // Controls reading and writing (for full and empty) >> Depends on the FIFO_DEPTH
  `define DATA_WIDTH 'd32              // # of data bits with parity

LBDR/ProposedMethod/step1_GeneratingST/SimulationTraceSetUpWithCOCOTB/rtl/LBDR.sv
/********************
* Filename:     LBDR.v
* Description:  LBDR with minimal support only (no deroutes and no forks). The input is 8 routing bits, two per output port, and 4 connectivity bits, one per output port
*
* $Revision: 25 $
* $Id: LBDR.v 25 2015-11-21 13:19:20Z ranga $
* $Date: 2015-11-21 15:19:20 +0200 (Sat, 21 Nov 2015) $
* $Author: ranga $
*********************/

`include "../include/parameters.sv"

module LBDR(clk, rst,
            empty,
            Rxy_rst, Cx_rst, 
            flit_id, dst_addr, cur_addr_rst,
            Nport, Eport, Wport, Sport, Lport
            );
            
  input clk, rst;
  input empty;
  input [7:0] Rxy_rst;
  input [3:0] Cx_rst;
  input [2:0] flit_id;
  input [3:0] dst_addr, cur_addr_rst;
  
  output logic Nport;
  output logic Wport;
  output logic Eport;
  output logic Sport;
  output logic Lport;
  
  // Declaring the local variables
  logic [7:0] Rxy = 'd60;
  logic [3:0] Cx = 'd15;
  logic [3:0] cur_addr = 'd5;

  // Assigning the Routing bits for 8 quadrants
  wire Rne = Rxy[0];
  wire Rnw = Rxy[1];
  wire Ren = Rxy[2];
  wire Res = Rxy[3];
  wire Rwn = Rxy[4];
  wire Rws = Rxy[5];
  wire Rse = Rxy[6];
  wire Rsw = Rxy[7];
  
  // Assigning the Connecting bits for 4 connections
  wire Cn = Cx[0];
  wire Ce = Cx[1];
  wire Cw = Cx[2];
  wire Cs = Cx[3];
  
  // Assigning the current and destination for XY co-ordinates
  wire [1:0] x_cur = cur_addr[1:0];
  wire [1:0] y_cur = cur_addr[3:2];
  wire [1:0] x_dst = dst_addr[1:0];
  wire [1:0] y_dst = dst_addr[3:2];
  
  always @ (posedge clk) begin
    if (rst) begin
      Rxy      <= Rxy_rst;
      Cx       <= Cx_rst;
      cur_addr <= cur_addr_rst;
      Nport <= 0;
      Eport <= 0;
      Wport <= 0;
      Sport <= 0;
      Lport <= 0;
    end
  end
  
  // Logic 1 -- Comparator logic checks the XY co-ordinates for current and destination and assigns the respective direction
  wire N1 = y_dst < y_cur;
  wire E1 = x_cur < x_dst;
  wire W1 = x_dst < x_cur;
  wire S1 = y_cur < y_dst;
  
  // Logic 2 -- The final output port direction based on the comparator logic and Routing, connecting bits
  // LBDR routing logic works on HEADER flit alone and it maintains the same port direction for PAYLOAD and TAIL flit of the same packet, until a new HEADER flit arrives
  
  always @ (posedge clk) begin
    if (rst || empty) begin
      {Nport, Eport, Wport, Sport, Lport} <= 0;
    end
    else if (flit_id == `HEADER) begin
      Nport <= ((N1 & ~E1 & ~W1) | (N1 & E1 & Rne) | (N1 & W1 & Rnw)) & Cn;
      Eport <= ((E1 & ~N1 & ~S1) | (E1 & N1 & Ren) | (E1 & S1 & Res)) & Ce;
      Wport <= ((W1 & ~N1 & ~S1) | (W1 & N1 & Rwn) | (W1 & S1 & Rws)) & Cw;
      Sport <= ((S1 & ~E1 & ~W1) | (S1 & E1 & Rse) | (S1 & W1 & Rsw)) & Cs;
      Lport <= ~N1 & ~ E1 & ~W1 & ~S1;
    end
  end
  
endmodule

LBDR/ProposedMethod/step1_GeneratingST/SimulationTraceSetUpWithCOCOTB/wrapper/LBDR_wrapper.sv
`timescale 1ns/1ps //timescale 

module LBDR_wrapper(
  output reg clk,
  input wire rst,
  input wire empty,
  input wire [7:0] Rxy_rst,
  input wire [3:0] Cx_rst,
  input wire [2:0] flit_id,
  input wire [3:0] dst_addr,
  input wire [3:0] cur_addr_rst,
  output wire Nport,
  output wire Wport,
  output wire Eport,
  output wire Sport,
  output wire Lport
  );


LBDR DUT_LBDR(
  .clk(clk), 
  .rst(rst),
  .empty(empty),
  .Rxy_rst(Rxy_rst),
  .Cx_rst(Cx_rst),
  .flit_id(flit_id),
  .dst_addr(dst_addr),
  .cur_addr_rst(cur_addr_rst),
  .Nport(Nport),
  .Wport(Wport),
  .Eport(Eport),
  .Sport(Sport),
  .Lport(Lport)
);

initial begin
	  $dumpfile("../gtkwave/LBDR_wave.vcd");
	  $dumpvars;
	  clk=1;
	  forever begin
		  #1 clk=~clk;
	  end
end
//print execution trace
initial begin
  integer fd;
  integer f;
  integer g;
  fd= $fopen("../simulation_traces/LBDR_input_output.txt");
  f= $fopen("../simulation_traces/LBDR_input.txt"); 
  $fwrite(fd,"rst,empty,[8bits]DUT_LBDR.Rxy,[4bits]DUT_LBDR.Cx,[3bits]flit_id,[4bits]dst_addr,[4bits]DUT_LBDR.cur_addr,DUT_LBDR.Rne,DUT_LBDR.Rnw,DUT_LBDR.Ren,DUT_LBDR.Res,DUT_LBDR.Rwn,DUT_LBDR.Rws,DUT_LBDR.Rse,DUT_LBDR.Rsw,DUT_LBDR.Cn,DUT_LBDR.Ce,DUT_LBDR.Cw,DUT_LBDR.Cs,DUT_LBDR.N1,DUT_LBDR.E1,DUT_LBDR.W1,DUT_LBDR.S1,[2bits]DUT_LBDR.x_cur,[2bits]DUT_LBDR.y_cur,[2bits]DUT_LBDR.x_dst,[2bits]DUT_LBDR.y_dst Nport,Eport,Wport,Sport,Lport\n");
  forever begin
    @(posedge clk);   
    $fwrite(fd, "%b%b%b%b%b%b%b%b%b%b%b%b%b%b%b%b%b%b%b%b%b%b%b%b%b%b%b %b%b%b%b%b\n",
			LBDR_wrapper.rst,LBDR_wrapper.empty,DUT_LBDR.Rxy,DUT_LBDR.Cx,
			LBDR_wrapper.flit_id,LBDR_wrapper.dst_addr,DUT_LBDR.cur_addr, 
			DUT_LBDR.Rne,DUT_LBDR.Rnw,DUT_LBDR.Ren,DUT_LBDR.Res,DUT_LBDR.Rwn,DUT_LBDR.Rws,DUT_LBDR.Rse,DUT_LBDR.Rsw,
			DUT_LBDR.Cn,DUT_LBDR.Ce,DUT_LBDR.Cw,DUT_LBDR.Cs,DUT_LBDR.N1,DUT_LBDR.E1,DUT_LBDR.W1,DUT_LBDR.S1,
			DUT_LBDR.x_cur,DUT_LBDR.y_cur,DUT_LBDR.x_dst,DUT_LBDR.y_dst,
			LBDR_wrapper.Nport,LBDR_wrapper.Eport,LBDR_wrapper.Wport,LBDR_wrapper.Sport,LBDR_wrapper.Lport); 		
    $fwrite(f, "%b%b%b%b%b%b%b\n",
			LBDR_wrapper.rst,LBDR_wrapper.empty,LBDR_wrapper.Rxy_rst,LBDR_wrapper.Cx_rst,
			LBDR_wrapper.flit_id,LBDR_wrapper.dst_addr,LBDR_wrapper.cur_addr_rst);		
  end
end
endmodule

LBDR/ProposedMethod/step1_GeneratingST/SimulationTraceSetUpWithCOCOTB/gtkwave/LBDR_wave.vcd
$date
	Mon Jun 19 10:36:14 2023
$end
$version
	Icarus Verilog
$end
$timescale
	1ps
$end
$scope module LBDR_wrapper $end
$var wire 4 ! Cx_rst [3:0] $end
$var wire 8 " Rxy_rst [7:0] $end
$var wire 4 # cur_addr_rst [3:0] $end
$var wire 4 $ dst_addr [3:0] $end
$var wire 1 % empty $end
$var wire 3 & flit_id [2:0] $end
$var wire 1 ' rst $end
$var wire 1 ( Wport $end
$var wire 1 ) Sport $end
$var wire 1 * Nport $end
$var wire 1 + Lport $end
$var wire 1 , Eport $end
$var reg 1 - clk $end
$scope module DUT_LBDR $end
$var wire 4 . Cx_rst [3:0] $end
$var wire 8 / Rxy_rst [7:0] $end
$var wire 1 - clk $end
$var wire 4 0 cur_addr_rst [3:0] $end
$var wire 4 1 dst_addr [3:0] $end
$var wire 1 % empty $end
$var wire 3 2 flit_id [2:0] $end
$var wire 1 ' rst $end
$var wire 2 3 y_dst [1:0] $end
$var wire 2 4 y_cur [1:0] $end
$var wire 2 5 x_dst [1:0] $end
$var wire 2 6 x_cur [1:0] $end
$var wire 1 7 W1 $end
$var wire 1 8 S1 $end
$var wire 1 9 Rws $end
$var wire 1 : Rwn $end
$var wire 1 ; Rsw $end
$var wire 1 < Rse $end
$var wire 1 = Rnw $end
$var wire 1 > Rne $end
$var wire 1 ? Res $end
$var wire 1 @ Ren $end
$var wire 1 A N1 $end
$var wire 1 B E1 $end
$var wire 1 C Cw $end
$var wire 1 D Cs $end
$var wire 1 E Cn $end
$var wire 1 F Ce $end
$var reg 4 G Cx [3:0] $end
$var reg 1 , Eport $end
$var reg 1 + Lport $end
$var reg 1 * Nport $end
$var reg 8 H Rxy [7:0] $end
$var reg 1 ) Sport $end
$var reg 1 ( Wport $end
$var reg 4 I cur_addr [3:0] $end
$upscope $end
$scope begin $unm_blk_8 $end
$var integer 32 J f [31:0] $end
$var integer 32 K fd [31:0] $end
$var integer 32 L g [31:0] $end
$upscope $end
$upscope $end
$enddefinitions $end
#0
$dumpvars
b1000 L
b10 K
b100 J
b101 I
b111100 H
b1111 G
1F
1E
1D
1C
0B
1A
1@
1?
0>
0=
0<
0;
1:
19
08
17
b1 6
b0 5
b1 4
b0 3
b1 2
b0 1
b0 0
b111100 /
b1111 .
1-
x,
x+
x*
x)
x(
1'
b1 &
0%
b0 $
b0 #
b111100 "
b1111 !
$end
#1000
0-
#2000
b1011 #
b1011 0
b11000011 "
b11000011 /
b10 &
b10 2
1%
07
b0 6
0A
b0 4
0+
0)
0(
0,
0*
b0 I
1-
#3000
0-
#4000
b11 #
b11 0
17
b11 6
1A
b10 4
1>
1=
0@
0?
0:
09
1<
1;
b1011 I
b11000011 H
1-
#5000
0-
#6000
b1110 #
b1110 0
0A
b0 4
b11 I
1-
#7000
0-
#8000
b1111 #
b1111 0
b10 6
1A
b11 4
b1110 I
1-
#9000
0-
#10000
b1000 #
b1000 0
b1 &
b1 2
0%
b11 6
b1111 I
1-
#11000
0-
#12000
b1110 #
b1110 0
b10 &
b10 2
1%
07
b0 6
b10 4
b1000 I
1-
#13000
0-
#14000
0'
17
b10 6
b11 4
b1110 I
1-
#15000
0-
#16000
1-
#17000
0-
#18000
0%
1-
#19000
0-
#20000
1%
1-
#21000
0-
#22000
b1001 #
b1001 0
b111100 "
b111100 /
1'
1-
#23000
0-
#24000
0'
b1 6
b10 4
0>
0=
1@
1?
1:
19
0<
0;
b1001 I
b111100 H
1-
#25000
0-
#26000
b1 &
b1 2
1-
#27000
0-
#28000
b111 #
b111 0
b10 &
b10 2
0%
1'
1-
#29000
0-
#30000
0'
b11 6
b1 4
b111 I
1-
#31000
0-
#32000
1-
#33000
0-
#34000
b101 #
b101 0
b1 &
b1 2
1%
1'
1-
#35000
0-
#36000
b10 &
b10 2
0%
0'
b1 6
b101 I
1-
#37000
0-
#38000
b1 &
b1 2
1-
#39000
0-
#40000
b11000011 "
b11000011 /
b10 &
b10 2
1'
1(
1-
#41000
0-
#42000
0'
1>
1=
0@
0?
0:
09
1<
1;
0(
b11000011 H
1-
#43000
0-
#44000
b0 #
b0 0
b111100 "
b111100 /
b1 &
b1 2
1%
1'
1-
#45000
0-
#46000
0'
07
b0 6
0A
b0 4
0>
0=
1@
1?
1:
19
0<
0;
b0 I
b111100 H
1-
#47000
0-
#48000
b11 #
b11 0
b10 &
b10 2
0%
1'
1-
#49000
0-
#50000
0'
17
b11 6
b11 I
1-
#51000
0-
#52000
1-
#53000
0-
#54000
b1 &
b1 2
1%
1-
#55000
0-
#56000
b10 &
b10 2
1-
#57000
0-
#58000
1-
#59000
0-
#60000
1'
1-
#61000
0-
#62000
0%
0'
1-
#63000
0-
#64000
b110 #
b110 0
1'
1-
#65000
0-
#66000
07
b10 5
b10 $
b10 1
b1 &
b1 2
0'
b10 6
1A
b1 4
b110 I
1-
#67000
0-
#68000
1%
1*
1-
#69000
0-
#70000
b1001 #
b1001 0
b11000011 "
b11000011 /
b10 &
b10 2
1'
0*
1-
#71000
0-
#72000
0%
0'
1B
b1 6
b10 4
1>
1=
0@
0?
0:
09
1<
1;
b1001 I
b11000011 H
1-
#73000
0-
#74000
b1000 #
b1000 0
b111100 "
b111100 /
b1 &
b1 2
1'
1-
#75000
0-
#76000
b11 #
b11 0
b11000011 "
b11000011 /
b10 &
b10 2
1%
b0 6
0>
0=
1@
1?
1:
19
0<
0;
b1000 I
b111100 H
1-
#77000
0-
#78000
b1111 #
b1111 0
b111100 "
b111100 /
0B
17
b11 6
0A
b0 4
1>
1=
0@
0?
0:
09
1<
1;
b11 I
b11000011 H
1-
#79000
0-
#80000
b1000 #
b1000 0
b1 &
b1 2
1A
b11 4
0>
0=
1@
1?
1:
19
0<
0;
b1111 I
b111100 H
1-
#81000
0-
#82000
b10 &
b10 2
0%
0'
1B
07
b0 6
b10 4
b1000 I
1-
#83000
0-
#84000
b11000011 "
b11000011 /
1'
1-
#85000
0-
#86000
b11 #
b11 0
b111100 "
b111100 /
1>
1=
0@
0?
0:
09
1<
1;
b11000011 H
1-
#87000
0-
#88000
b1110 #
b1110 0
b11000011 "
b11000011 /
0B
17
b11 6
0A
b0 4
0>
0=
1@
1?
1:
19
0<
0;
b11 I
b111100 H
1-
#89000
0-
#90000
b11 #
b11 0
b111100 "
b111100 /
1%
07
b10 6
1A
b11 4
1>
1=
0@
0?
0:
09
1<
1;
b1110 I
b11000011 H
1-
#91000
0-
#92000
b111 #
b111 0
b11000011 "
b11000011 /
b1 &
b1 2
0%
17
b11 6
0A
b0 4
0>
0=
1@
1?
1:
19
0<
0;
b11 I
b111100 H
1-
#93000
0-
#94000
b10 &
b10 2
1%
0'
1A
b1 4
1>
1=
0@
0?
0:
09
1<
1;
b111 I
b11000011 H
1-
#95000
0-
#96000
07
b11 5
b11 $
b11 1
b1 &
b1 2
0%
1-
#97000
0-
#98000
b10 &
b10 2
1%
1*
1-
#99000
0-
#100000
b110 #
b110 0
b1 &
b1 2
1'
0*
1-
#101000
0-
#102000
0'
1B
b10 6
b110 I
1-
#103000
0-
#104000
b101 #
b101 0
b10 &
b10 2
1'
1-
#105000
0-
#106000
b1010 #
b1010 0
b111100 "
b111100 /
0%
b1 6
b101 I
1-
#107000
0-
#108000
b100 #
b100 0
b11000011 "
b11000011 /
1%
b10 6
b10 4
0>
0=
1@
1?
1:
19
0<
0;
b1010 I
b111100 H
1-
#109000
0-
#110000
b1 #
b1 0
b111100 "
b111100 /
b1 &
b1 2
b0 6
b1 4
1>
1=
0@
0?
0:
09
1<
1;
b100 I
b11000011 H
1-
#111000
0-
#112000
b10 &
b10 2
0%
0'
b1 6
0A
b0 4
0>
0=
1@
1?
1:
19
0<
0;
b1 I
b111100 H
1-
#113000
0-
#114000
0B
b1 5
18
b10 3
b1001 $
b1001 1
b1 &
b1 2
1-
#115000
0-
#116000
b1011 #
b1011 0
b11000011 "
b11000011 /
1%
1'
1)
1-
#117000
0-
#118000
b10 &
b10 2
0%
0'
17
b11 6
08
b10 4
1>
1=
0@
0?
0:
09
1<
1;
0)
b1011 I
b11000011 H
1-
#119000
0-
#120000
1-
#121000
0-
#122000
b100 #
b100 0
b111100 "
b111100 /
1%
1'
1-
#123000
0-
#124000
b11 #
b11 0
b11000011 "
b11000011 /
0%
1B
07
b0 6
18
b1 4
0>
0=
1@
1?
1:
19
0<
0;
b100 I
b111100 H
1-
#125000
0-
#126000
b11 3
b1101 $
b1101 1
b1 &
b1 2
0'
0B
17
b11 6
b0 4
1>
1=
0@
0?
0:
09
1<
1;
b11 I
b11000011 H
1-
#127000
0-
#128000
b1 3
b101 $
b101 1
1)
1-
#129000
0-
#130000
b1010 #
b1010 0
b10 &
b10 2
1'
1-
#131000
0-
#132000
0'
b10 6
1A
08
b10 4
b1010 I
0)
1-
#133000
0-
#134000
b1 &
b1 2
1%
1-
#135000
0-
#136000
b10 &
b10 2
0%
1-
#137000
0-
#138000
1%
1-
#139000
0-
#140000
0%
1-
#141000
0-
#142000
b111 #
b111 0
1'
1-
#143000
0-
#144000
0'
b11 6
0A
b1 4
b111 I
1-
#145000
0-
#146000
1-
#147000
0-
#148000
b1 &
b1 2
1%
1-
#149000
0-
#150000
18
b10 3
b1001 $
b1001 1
0%
1-
#151000
0-
#152000
b10 &
b10 2
1%
1)
1-
#153000
0-
#154000
b101 #
b101 0
0%
1'
0)
1-
#155000
0-
#156000
b11 #
b11 0
b1 &
b1 2
07
b1 6
b101 I
1-
#157000
0-
#158000
b10 &
b10 2
0'
17
b11 6
b0 4
b11 I
1-
#159000
0-
#160000
b100 #
b100 0
b111100 "
b111100 /
1%
1'
1-
#161000
0-
#162000
b1000 #
b1000 0
1B
07
b0 6
b1 4
0>
0=
1@
1?
1:
19
0<
0;
b100 I
b111100 H
1-
#163000
0-
#164000
0%
0'
08
b10 4
b1000 I
1-
#165000
0-
#166000
1%
1-
#167000
0-
#168000
1-
#169000
0-
#170000
0%
1-
#171000
0-
#172000
b1 &
b1 2
1%
1-
#173000
0-
#174000
0B
b0 5
1A
b0 3
b0 $
b0 1
0%
1-
#175000
0-
#176000
b0 #
b0 0
b10 &
b10 2
1'
1*
1-
#177000
0-
#178000
b1111 #
b1111 0
b1 &
b1 2
0A
b0 4
0*
b0 I
1-
#179000
0-
#180000
b1011 #
b1011 0
b11000011 "
b11000011 /
17
b11 6
1A
b11 4
b1111 I
1-
#181000
0-
#182000
b1111 #
b1111 0
1%
b10 4
1>
1=
0@
0?
0:
09
1<
1;
b1011 I
b11000011 H
1-
#183000
0-
#184000
b101 #
b101 0
0%
b11 4
b1111 I
1-
#185000
0-
#186000
b110 #
b110 0
b111100 "
b111100 /
b10 &
b10 2
b1 6
b1 4
b101 I
1-
#187000
0-
#188000
0'
b10 6
0>
0=
1@
1?
1:
19
0<
0;
b110 I
b111100 H
1-
#189000
0-
#190000
b1 &
b1 2
1%
1-
#191000
0-
#192000
b1 #
b1 0
b11000011 "
b11000011 /
b10 &
b10 2
0%
1'
1-
#193000
0-
#194000
1%
0'
b1 6
0A
b0 4
1>
1=
0@
0?
0:
09
1<
1;
b1 I
b11000011 H
1-
#195000
0-
#196000
0%
1-
#197000
0-
#198000
b1 &
b1 2
1%
1-
#199000
0-
#200000
18
b11 3
b1100 $
b1100 1
0%
1-
#201000
0-
#202000
b110 #
b110 0
1'
1)
1-
#203000
0-
#204000
1B
07
b11 5
b10 3
b1011 $
b1011 1
0'
b10 6
b1 4
b110 I
0)
1-
#205000
0-
#206000
0B
17
b1 5
b11 3
b1101 $
b1101 1
1)
1-
#207000
0-
#208000
b1111 #
b1111 0
b111100 "
b111100 /
b10 &
b10 2
1%
1'
1-
#209000
0-
#210000
0'
b11 6
08
b11 4
0>
0=
1@
1?
1:
19
0<
0;
0)
b1111 I
b111100 H
1-
#211000
0-
#212000
0%
1-
#213000
0-
#214000
1%
1-
#215000
0-
#216000
b10 5
1A
b1 3
b110 $
b110 1
b1 &
b1 2
0%
1-
#217000
0-
#218000
1%
1(
1-
#219000
0-
#220000
b10 &
b10 2
0(
1-
#221000
0-
#222000
b10 #
b10 0
b11000011 "
b11000011 /
1'
1-
#223000
0-
#224000
b1011 #
b1011 0
0%
07
b10 6
0A
18
b0 4
1>
1=
0@
0?
0:
09
1<
1;
b10 I
b11000011 H
1-
#225000
0-
#226000
b1001 #
b1001 0
b111100 "
b111100 /
b1 &
b1 2
17
b11 6
1A
08
b10 4
b1011 I
1-
#227000
0-
#228000
1%
0'
1B
07
b1 6
0>
0=
1@
1?
1:
19
0<
0;
b1001 I
b111100 H
1-
#229000
0-
#230000
b10 &
b10 2
1-
#231000
0-
#232000
b1 &
b1 2
1-
#233000
0-
#234000
b1010 #
b1010 0
b11000011 "
b11000011 /
b10 &
b10 2
1'
1-
#235000
0-
#236000
b1100 #
b1100 0
b111100 "
b111100 /
0%
0B
b10 6
1>
1=
0@
0?
0:
09
1<
1;
b1010 I
b11000011 H
1-
#237000
0-
#238000
b1 &
b1 2
1%
0'
1B
b0 6
b11 4
0>
0=
1@
1?
1:
19
0<
0;
b1100 I
b111100 H
1-
#239000
0-
#240000
b11 5
b0 3
b11 $
b11 1
0%
1-
#241000
0-
#242000
0B
b0 5
b1 3
b100 $
b100 1
1,
1-
#243000
0-
#244000
1B
b11 5
b10 3
b1011 $
b1011 1
0,
1*
1-
#245000
0-
#246000
b1110 #
b1110 0
b11000011 "
b11000011 /
1'
1,
0*
1-
#247000
0-
#248000
b10 &
b10 2
0'
b10 6
1>
1=
0@
0?
0:
09
1<
1;
b1110 I
b11000011 H
0,
1-
#249000
0-
#250000
0B
b10 5
b1 3
b110 $
b110 1
b1 &
b1 2
1-
#251000
0-
#252000
b1010 #
b1010 0
b10 &
b10 2
1'
1*
1-
#253000
0-
#254000
b0 #
b0 0
b111100 "
b111100 /
b1 &
b1 2
b10 4
0*
b1010 I
1-
#255000
0-
#256000
b10 &
b10 2
1%
1B
b0 6
0A
18
b0 4
0>
0=
1@
1?
1:
19
0<
0;
b0 I
b111100 H
1-
#257000
0-
#258000
b1 5
b10 3
b1001 $
b1001 1
b1 &
b1 2
0%
0'
1-
#259000
0-
#260000
b10 &
b10 2
1%
1,
1-
#261000
0-
#262000
b1 #
b1 0
b11000011 "
b11000011 /
b1 &
b1 2
0%
1'
0,
1-
#263000
0-
#264000
b1111 #
b1111 0
1%
0B
b1 6
1>
1=
0@
0?
0:
09
1<
1;
b1 I
b11000011 H
1-
#265000
0-
#266000
b10 &
b10 2
0%
0'
17
b11 6
1A
08
b11 4
b1111 I
1-
#267000
0-
#268000
b10 5
0A
b11 3
b1110 $
b1110 1
b1 &
b1 2
1-
#269000
0-
#270000
b0 5
b1100 $
b1100 1
1(
1-
#271000
0-
#272000
b110 #
b110 0
b111100 "
b111100 /
b10 &
b10 2
1%
1'
1-
#273000
0-
#274000
b11 #
b11 0
b11000011 "
b11000011 /
b1 &
b1 2
b10 6
18
b1 4
0>
0=
1@
1?
1:
19
0<
0;
0(
b110 I
b111100 H
1-
#275000
0-
#276000
b10 #
b10 0
0%
b11 6
b0 4
1>
1=
0@
0?
0:
09
1<
1;
b11 I
b11000011 H
1-
#277000
0-
#278000
b10 &
b10 2
0'
b10 6
b10 I
1-
#279000
0-
#280000
1-
#281000
0-
#282000
b1 &
b1 2
1%
1-
#283000
0-
#284000
b1000 #
b1000 0
b111100 "
b111100 /
1'
1-
#285000
0-
#286000
b110 #
b110 0
b11000011 "
b11000011 /
b10 &
b10 2
0%
07
b0 6
b10 4
0>
0=
1@
1?
1:
19
0<
0;
b1000 I
b111100 H
1-
#287000
0-
#288000
1%
17
b10 6
b1 4
1>
1=
0@
0?
0:
09
1<
1;
b110 I
b11000011 H
1-
#289000
0-
#290000
b1001 #
b1001 0
1-
#291000
0-
#292000
0%
0'
b1 6
b10 4
b1001 I
1-
#293000
0-
#294000
1-
#295000
0-
#296000
b1110 #
b1110 0
b1 &
b1 2
1%
1'
1-
#297000
0-
#298000
b100 #
b100 0
b111100 "
b111100 /
b10 &
b10 2
b10 6
08
b11 4
b1110 I
1-
#299000
0-
#300000
0%
0'
07
b0 6
18
b1 4
0>
0=
1@
1?
1:
19
0<
0;
b100 I
b111100 H
1-
#301000
0-
#302000
1%
1-
#303000
0-
#304000
b1 &
b1 2
1-
#305000
0-
#306000
b1101 #
b1101 0
b10 &
b10 2
1'
1-
#307000
0-
#308000
b10 #
b10 0
b11000011 "
b11000011 /
0%
17
b1 6
08
b11 4
b1101 I
1-
#309000
0-
#310000
b1001 #
b1001 0
b1 &
b1 2
b10 6
18
b0 4
1>
1=
0@
0?
0:
09
1<
1;
b10 I
b11000011 H
1-
#311000
0-
#312000
b10 &
b10 2
1%
0'
b1 6
b10 4
b1001 I
1-
#313000
0-
#314000
b1110 #
b1110 0
b1 &
b1 2
1'
1-
#315000
0-
#316000
b10 &
b10 2
0%
0'
b10 6
08
b11 4
b1110 I
1-
#317000
0-
#318000
b1 &
b1 2
1%
1-
#319000
0-
#320000
b10 &
b10 2
1-
#321000
0-
#322000
b1011 #
b1011 0
b111100 "
b111100 /
b1 &
b1 2
1'
1-
#323000
0-
#324000
0'
b11 6
18
b10 4
0>
0=
1@
1?
1:
19
0<
0;
b1011 I
b111100 H
1-
#325000
0-
#326000
b1101 #
b1101 0
b11000011 "
b11000011 /
1'
1-
#327000
0-
#328000
0'
b1 6
08
b11 4
1>
1=
0@
0?
0:
09
1<
1;
b1101 I
b11000011 H
1-
#329000
0-
#330000
b1100 #
b1100 0
b10 &
b10 2
1'
1-
#331000
0-
#332000
1B
b10 5
1A
b10 3
b1010 $
b1010 1
b1 &
b1 2
0%
0'
07
b0 6
b1100 I
1-
#333000
0-
#334000
b10 &
b10 2
1*
1-
#335000
0-
#336000
1-
#337000
0-
#338000
1%
1-
#339000
0-
#340000
0*
1-
#341000
0-
#342000
b11 5
b0 3
b11 $
b11 1
b1 &
b1 2
0%
1-
#343000
0-
#344000
b1010 #
b1010 0
b10 &
b10 2
1%
1'
1*
1-
#345000
0-
#346000
b1 &
b1 2
0'
b10 6
b10 4
0*
b1010 I
1-
#347000
0-
#348000
b1100 #
b1100 0
b111100 "
b111100 /
b10 &
b10 2
0%
1'
1-
#349000
0-
#350000
b1 &
b1 2
1%
0'
b0 6
b11 4
0>
0=
1@
1?
1:
19
0<
0;
b1100 I
b111100 H
1-
#351000
0-
#352000
b11000011 "
b11000011 /
b10 &
b10 2
0%
1'
1-
#353000
0-
#354000
b1011 #
b1011 0
b111100 "
b111100 /
b1 &
b1 2
1%
1>
1=
0@
0?
0:
09
1<
1;
b11000011 H
1-
#355000
0-
#356000
0'
0B
b11 6
b10 4
0>
0=
1@
1?
1:
19
0<
0;
b1011 I
b111100 H
1-
#357000
0-
#358000
b10 &
b10 2
1-
#359000
0-
#360000
b11 #
b11 0
b11000011 "
b11000011 /
1'
1-
#361000
0-
#362000
b10 #
b10 0
b111100 "
b111100 /
b1 &
b1 2
0%
0A
b0 4
1>
1=
0@
0?
0:
09
1<
1;
b11 I
b11000011 H
1-
#363000
0-
#364000
b10 &
b10 2
1%
0'
1B
b10 6
0>
0=
1@
1?
1:
19
0<
0;
b10 I
b111100 H
1-
#365000
0-
#366000
1-
#367000
0-
#368000
b11000011 "
b11000011 /
b1 &
b1 2
1'
1-
#369000
0-
#370000
b10 &
b10 2
0%
0'
1>
1=
0@
0?
0:
09
1<
1;
b11000011 H
1-
#371000
0-
#372000
1%
1-
#373000
0-
#374000
0B
17
b1 5
18
b11 3
b1101 $
b1101 1
b1 &
b1 2
0%
1-
#375000
0-
#376000
b110 #
b110 0
b10 &
b10 2
1'
1)
1-
#377000
0-
#378000
b1010 #
b1010 0
b111100 "
b111100 /
b1 &
b1 2
b1 4
0)
b110 I
1-
#379000
0-
#380000
b11 #
b11 0
b10 &
b10 2
b10 4
0>
0=
1@
1?
1:
19
0<
0;
b1010 I
b111100 H
1-
#381000
0-
#382000
b1 &
b1 2
1%
0'
b11 6
b0 4
b11 I
1-
#383000
0-
#384000
b10 &
b10 2
1'
1-
#385000
0-
#386000
0'
1-
#387000
0-
#388000
b1110 #
b1110 0
1'
1-
#389000
0-
#390000
b1010 #
b1010 0
b1 &
b1 2
0%
b10 6
08
b11 4
b1110 I
1-
#391000
0-
#392000
1%
0'
18
b10 4
b1010 I
1-
#393000
0-
#394000
b0 5
1A
08
b0 3
b0 $
b0 1
0%
1-
#395000
0-
#396000
b10 &
b10 2
1%
1(
1-
#397000
0-
#398000
0(
1-
#399000
0-
#400000
b1 &
b1 2
1-
#401000
0-
#402000
1-
#403000
0-
#404000
b1110 #
b1110 0
1'
1-
#405000
0-
#406000
b1100 #
b1100 0
b11000011 "
b11000011 /
b11 4
b1110 I
1-
#407000
0-
#408000
b1010 #
b1010 0
b10 &
b10 2
07
b0 6
1>
1=
0@
0?
0:
09
1<
1;
b1100 I
b11000011 H
1-
#409000
0-
#410000
b100 #
b100 0
b111100 "
b111100 /
17
b10 6
b10 4
b1010 I
1-
#411000
0-
#412000
0%
0'
07
b0 6
b1 4
0>
0=
1@
1?
1:
19
0<
0;
b100 I
b111100 H
1-
#413000
0-
#414000
b1110 #
b1110 0
1'
1-
#415000
0-
#416000
b1111 #
b1111 0
b1 &
b1 2
17
b10 6
b11 4
b1110 I
1-
#417000
0-
#418000
b100 #
b100 0
b11000011 "
b11000011 /
b10 &
b10 2
1%
b11 6
b1111 I
1-
#419000
0-
#420000
b1111 #
b1111 0
b111100 "
b111100 /
0%
07
b0 6
b1 4
1>
1=
0@
0?
0:
09
1<
1;
b100 I
b11000011 H
1-
#421000
0-
#422000
0A
b11 3
b1100 $
b1100 1
b1 &
b1 2
0'
17
b11 6
b11 4
0>
0=
1@
1?
1:
19
0<
0;
b1111 I
b111100 H
1-
#423000
0-
#424000
b110 #
b110 0
b11000011 "
b11000011 /
b10 &
b10 2
1%
1'
1(
1-
#425000
0-
#426000
b101 #
b101 0
b1 &
b1 2
0%
b10 6
18
b1 4
1>
1=
0@
0?
0:
09
1<
1;
0(
b110 I
b11000011 H
1-
#427000
0-
#428000
b1010 #
b1010 0
b1 6
b101 I
1-
#429000
0-
#430000
1%
0'
b10 6
b10 4
b1010 I
1-
#431000
0-
#432000
b1 5
b1101 $
b1101 1
0%
1-
#433000
0-
#434000
b1110 #
b1110 0
b10 &
b10 2
1%
1'
1)
1-
#435000
0-
