Arbiter/Arbiter_goldminer_result/verilog/Arbiter/Arbiter.v

module Arbiter (clk, 
                rst, 
                Req_N, Req_E, Req_W, Req_S, Req_L, // From LBDR modules (routing logic)
                DCTS, // Getting the CTS signal from the input FIFO of the next router/NI (for hand-shaking)
                Grant_N, Grant_E, Grant_W, Grant_S, Grant_L, // Grants given to LBDR (routing logic) requests (encoded as one-hot)
                Xbar_sel, // select lines for XBAR (crossbar switch)
                RTS // Valid output which is sent to the next router/NI to specify that the data on the output port is valid
            );


    input   clk, rst;
    input   Req_N, Req_E, Req_W, Req_S, Req_L;
    input   DCTS;
    output  reg Grant_N, Grant_E, Grant_W, Grant_S, Grant_L;
    output  reg [4:0] Xbar_sel;
    output  wire RTS;

    //typedef enum bit [5:0] {IDLE = 6'b000001, Local = 6'b000010, North = 6'b000100, East = 6'b001000, West = 6'b010000, South = 6'b100000} STATE_TYPE;
	
	parameter [5:0] IDLE = 6'b000001;
	parameter [5:0] Local = 6'b000010;
	parameter [5:0] North = 6'b000100;
	parameter [5:0] East = 6'b001000;
	parameter [5:0] West = 6'b010000;
	parameter [5:0] South = 6'b100000;

    reg [5:0] state = IDLE;
    reg [5:0] state_in = IDLE;
    reg [5:0] next_state = IDLE;

    reg RTS_FF = 0;
    reg RTS_FF_in = 0;


    // Sequential part
    // rst is active high!
    always @(posedge clk) begin

     if (rst) begin
        state  <= IDLE;
        RTS_FF <= 0;
     end
     else begin
        // no grant given yet, it might be that there is no request to 
        // arbiter or request is there, but the next router's/NI's FIFO is full
        state <= state_in;
        RTS_FF <= RTS_FF_in;   
      end
    end 


    // Anything below here is pure combinational

    assign RTS = RTS_FF;

    always @(RTS_FF, DCTS, state, next_state) begin
        if (RTS_FF && !DCTS) 
            state_in <= state;
        else
            state_in <= next_state;
    end


    always @(state, RTS_FF, DCTS) begin
        if (state == IDLE) begin 
            RTS_FF_in <= 0;
            // if there was a grant given to one of the inputs, 
            // tell the next router/NI that the output data is valid
        end
        else begin
            if (RTS_FF && DCTS)
                RTS_FF_in <= 0;
            else 
                RTS_FF_in <= 1;
        end
    end

    // Sets the grants using round robin 
    // the order is   L --> N --> E --> W --> S  and  back to L
    always @(state, Req_N, Req_E, Req_W, Req_S, Req_L, DCTS, RTS_FF) begin
        Grant_N  <= 0;
        Grant_E  <= 0;
        Grant_W  <= 0;
        Grant_S  <= 0;
        Grant_L  <= 0;
        Xbar_sel <= 5'b00000; 

        case(state)
            IDLE: begin
                Xbar_sel<= 5'b00000; 
                
                if (Req_L) 
                    next_state <= Local;
                else if (Req_N) 
                    next_state <= North;         
                else if (Req_E) 
                    next_state <= East;
                else if (Req_W) 
                    next_state <= West;
                else if (Req_S) 
                    next_state <= South;
                else
                    next_state <= IDLE;
            end

            North: begin
                Grant_N <= DCTS & RTS_FF ;
                Xbar_sel<= 5'b00001;
                
                if (Req_N)  
                    next_state <= North; 
                else if (Req_E) 
                    next_state <= East;
                else if (Req_W) 
                    next_state <= West;
                else if (Req_S) 
                    next_state <= South;
                else if (Req_L) 
                    next_state <= Local;
                else
                    next_state <= IDLE; 
            end 

            East: begin
                Grant_E <= DCTS & RTS_FF;
                Xbar_sel<= 5'b00010;
                
                if (Req_E)  
                    next_state <= East; 
                else if (Req_W) 
                    next_state <= West;
                else if (Req_S) 
                    next_state <= South;
                else if (Req_L) 
                    next_state <= Local;
                else if (Req_N) 
                    next_state <= North;
                else
                    next_state <= IDLE; 
            end 

            West: begin
                Grant_W <= DCTS & RTS_FF;
                Xbar_sel<= 5'b00100;
                
                if (Req_W ) 
                    next_state <= West; 
                else if (Req_S ) 
                    next_state <= South;
                else if (Req_L ) 
                    next_state <= Local;
                else if (Req_N ) 
                    next_state <= North;
                else if (Req_E ) 
                    next_state <= East;
                else
                    next_state <= IDLE; 
            end

            South: begin
                Grant_S <= DCTS & RTS_FF;
                Xbar_sel<= 5'b01000;
                
                if (Req_S )
                    next_state <= South; 
                else if (Req_L)
                    next_state <= Local;
                else if (Req_N)
                    next_state <= North;
                else if (Req_E)
                    next_state <= East;
                else if (Req_W)
                    next_state <= West;
                else
                    next_state <= IDLE; 
            end

            default: begin // Including Local and invalid states (non- onehot!)
                Grant_L <= DCTS & RTS_FF;
                Xbar_sel<= 5'b10000;
                
                if (Req_L)
                    next_state <= Local; 
                else if (Req_N)
                    next_state <= North;         
                else if (Req_E )
                    next_state <= East;
                else if (Req_W )
                    next_state <= West;
                else if (Req_S )
                    next_state <= South;
                else
                    next_state <= IDLE; 
            end
        endcase
    end

endmodule

Arbiter/Arbiter_goldminer_result/RunTime/goldmine.out/Arbiter/Arbiter_bench.v
`timescale 1ns/1ps

module Arbiter_bench();

reg DEFAULT_RESET;
reg Req_S;
reg Req_E;
reg Req_W;
reg rst;
reg DCTS;
reg clk;
reg Req_L;
reg Req_N;

wire Grant_L;
wire Grant_N;
wire RTS;
wire Grant_E;
wire [4:0] Xbar_sel;
wire Grant_W;
wire Grant_S;

Arbiter Arbiter_ (
	.Req_S(Req_S),
	.Req_E(Req_E),
	.Req_W(Req_W),
	.rst(rst),
	.DCTS(DCTS),
	.clk(clk),
	.Req_L(Req_L),
	.Req_N(Req_N),
	.Grant_L(Grant_L),
	.Grant_N(Grant_N),
	.RTS(RTS),
	.Grant_E(Grant_E),
	.Xbar_sel(Xbar_sel),
	.Grant_W(Grant_W),
	.Grant_S(Grant_S));

	initial begin
		$dumpfile("/home/hrostami/Arbiter_goldminer/goldminer/RunTime/goldmine.out/Arbiter/Arbiter.vcd");
		$dumpvars(0, Arbiter_bench.Arbiter_);
		clk = 1;
		DEFAULT_RESET = 1;
		#26;
		DEFAULT_RESET = 0;
		#68300 $finish;
	end

	always begin
		#25 clk = ~clk;
	end

	always begin
		#24;
		Req_S = $random;
		Req_E = $random;
		Req_W = $random;
		rst = $random;
		DCTS = $random;
		Req_L = $random;
		Req_N = $random;
		#26;
	end

endmodule

Arbiter/Arbiter_goldminer_result/RunTime/goldmine.out/Arbiter/Arbiter.vcd
$date
	Sat Jun 17 19:36:09 2023
$end
$version
	Icarus Verilog
$end
$timescale
	1ps
$end
$scope module Arbiter_bench $end
$scope module Arbiter_ $end
$var wire 1 ! DCTS $end
$var wire 1 " RTS $end
$var wire 1 # Req_E $end
$var wire 1 $ Req_L $end
$var wire 1 % Req_N $end
$var wire 1 & Req_S $end
$var wire 1 ' Req_W $end
$var wire 1 ( clk $end
$var wire 1 ) rst $end
$var reg 1 * Grant_E $end
$var reg 1 + Grant_L $end
$var reg 1 , Grant_N $end
$var reg 1 - Grant_S $end
$var reg 1 . Grant_W $end
$var reg 1 / RTS_FF $end
$var reg 1 0 RTS_FF_in $end
$var reg 5 1 Xbar_sel [4:0] $end
$var reg 6 2 next_state [5:0] $end
$var reg 6 3 state [5:0] $end
$var reg 6 4 state_in [5:0] $end
$upscope $end
$upscope $end
$enddefinitions $end
#0
$dumpvars
b1 4
b1 3
b1 2
b0 1
00
0/
0.
0-
0,
0+
0*
x)
1(
x'
x&
x%
x$
x#
0"
x!
$end
#24000
b10 4
b10 2
1%
1$
1!
1)
1'
1#
0&
#25000
0(
#50000
1(
#74000
0%
0)
#75000
0(
#100000
b10000 1
10
b10 3
1(
#124000
b10000 1
0#
1&
#125000
0(
#150000
1+
b10000 1
00
1"
1/
1(
#174000
b100 4
b100 2
b10000 1
1+
1%
0$
0'
#175000
0(
#200000
b1 1
0+
10
0"
0/
b100 3
1(
#224000
b1000 4
b1000 2
b1 1
0%
0!
1'
1#
#225000
0(
#250000
b10 1
1"
1/
b1000 3
1(
#274000
b10000 4
00
b10000 2
1*
b10 1
1%
1$
1!
1)
0#
#275000
0(
#300000
b10 4
b10 2
b0 1
0*
0"
0/
b1 3
1(
#324000
b10000 4
b10000 2
0%
0$
0&
#325000
0(
#350000
1(
#374000
b100 4
b100 2
1%
0!
0'
#375000
0(
#400000
1(
#424000
0)
1&
#425000
0(
#450000
b1 1
10
b100 3
1(
#474000
b1 1
1)
1'
1#
#475000
0(
#500000
b0 1
00
b1 3
1(
#524000
b10 4
b10 2
0%
1$
1!
0)
0'
#525000
0(
#550000
b10000 1
10
b10 3
1(
#574000
1)
#575000
0(
#600000
b0 1
00
b1 3
1(
#624000
b100 4
b100 2
1%
0$
0!
0)
#625000
0(
#650000
b1 1
10
b100 3
1(
#674000
b1 1
1$
1!
1)
0#
#675000
0(
#700000
b10 4
b10 2
b0 1
00
b1 3
1(
#724000
b10000 4
b10000 2
0%
0$
1'
#725000
0(
#750000
1(
#774000
b10 4
b10 2
1%
1$
0!
0)
0'
0&
#775000
0(
#800000
b10000 1
10
b10 3
1(
#824000
b10000 1
0%
1!
1'
1#
1&
#825000
0(
#850000
1+
b10000 1
00
1"
1/
1(
#874000
b10000 1
1+
1%
0&
#875000
0(
#900000
b10000 1
0+
10
0"
0/
1(
#924000
b100000 4
b100000 2
b10000 1
0%
0$
0'
0#
1&
#925000
0(
#950000
1-
b1000 1
00
1"
1/
b100000 3
1(
#974000
10
b10 2
b1000 1
0-
1$
0!
1'
1#
0&
#975000
0(
#1000000
1(
#1024000
b1000 1
0#
#1025000
0(
#1050000
1(
#1074000
00
b100000 4
b100000 2
1-
b1000 1
0$
1!
1)
1#
1&
#1075000
0(
#1100000
b1000 4
b1000 2
b0 1
0-
0"
0/
b1 3
1(
#1124000
b10 4
b10 2
1$
0)
0'
0&
#1125000
0(
#1150000
b10000 1
10
b10 3
1(
#1174000
b10000 4
b10000 2
b10000 1
0$
0!
1)
1'
0#
#1175000
0(
#1200000
b0 1
00
b1 3
1(
#1224000
b10 4
b10 2
1$
0)
0'
1#
1&
#1225000
0(
#1250000
b10000 1
10
b10 3
1(
#1274000
b10000 1
0&
#1275000
0(
#1300000
b10000 1
1"
1/
1(
#1324000
b100 2
b10000 1
1%
0$
1&
#1325000
0(
#1350000
1(
#1374000
00
b10 4
b10 2
1+
b10000 1
1$
1!
0#
0&
#1375000
0(
#1400000
b10000 1
0+
10
0"
0/
1(
#1424000
b100 4
b100 2
b10000 1
0$
0!
1)
1'
1#
#1425000
0(
#1450000
b0 1
00
b1 3
1(
#1474000
b10 4
b10 2
1$
1&
#1475000
0(
#1500000
1(
#1524000
0%
1!
0)
0'
0#
0&
#1525000
0(
#1550000
b10000 1
10
b10 3
1(
#1574000
b1000 4
b1000 2
b10000 1
0$
1#
#1575000
0(
#1600000
1*
b10 1
00
1"
1/
b1000 3
1(
#1624000
b100000 4
b100000 2
b10 1
1*
1$
1)
0#
1&
#1625000
0(
#1650000
b10 4
b10 2
b0 1
0*
0"
0/
b1 3
1(
#1674000
0!
0)
1'
0&
#1675000
0(
#1700000
b10000 1
10
b10 3
1(
#1724000
b1 4
b1 2
b10000 1
0$
1)
0'
#1725000
0(
#1750000
b0 1
00
b1 3
1(
#1774000
b10 4
b10 2
1%
1$
1!
1#
1&
#1775000
0(
#1800000
1(
#1824000
b100 4
b100 2
0$
0!
1'
0&
#1825000
0(
#1850000
1(
#1874000
0#
#1875000
0(
#1900000
1(
#1924000
b10 4
b10 2
0%
1$
1!
0)
#1925000
0(
#1950000
b10000 1
10
b10 3
1(
#1974000
b10000 1
0!
1&
#1975000
0(
#2000000
b10000 1
1"
1/
1(
#2024000
00
1+
b10000 1
1%
1!
1)
0&
#2025000
0(
#2050000
b0 1
0+
0"
0/
b1 3
1(
#2074000
b1000 4
b1000 2
0%
0$
0!
1#
#2075000
0(
#2100000
1(
#2124000
b10 4
b10 2
1%
1$
1!
0'
0#
#2125000
0(
#2150000
1(
#2174000
0)
1'
1#
1&
#2175000
0(
#2200000
b10000 1
10
b10 3
1(
#2224000
b1000 4
b1000 2
b10000 1
0%
0$
1)
#2225000
0(
#2250000
b0 1
00
b1 3
1(
#2274000
b100 4
b100 2
1%
0!
0)
0'
#2275000
0(
#2300000
b1 1
10
b100 3
1(
#2324000
b1 1
0#
0&
#2325000
0(
#2350000
b1 1
1"
1/
1(
#2374000
b10000 2
b1 1
0%
1'
#2375000
0(
#2400000
1(
#2424000
00
b100 4
b100 2
1,
b1 1
1%
1!
1)
1#
1&
#2425000
0(
#2450000
b0 1
0,
0"
0/
b1 3
1(
#2474000
0!
0'
#2475000
0(
#2500000
1(
#2524000
b10 4
b10 2
0%
1$
0)
1'
0#
#2525000
0(
#2550000
b10000 1
10
b10 3
1(
#2574000
b10000 1
1%
1!
1)
0'
0&
#2575000
0(
#2600000
b0 1
00
b1 3
1(
#2624000
1'
1#
#2625000
0(
#2650000
1(
#2674000
b10000 4
b10000 2
0%
0$
0)
0#
1&
#2675000
0(
#2700000
b100 1
10
b10000 3
1(
#2724000
b100000 4
b100000 2
b100 1
1%
0!
0'
#2725000
0(
#2750000
b1000 1
1"
1/
b100000 3
1(
#2774000
b100 2
b1000 1
0&
#2775000
0(
#2800000
1(
#2824000
00
b100 4
1-
b1000 1
1!
1#
#2825000
0(
#2850000
b1 1
0-
10
0"
0/
b100 3
1(
#2874000
b10000 4
b10000 2
b1 1
0%
1'
0#
1&
#2875000
0(
#2900000
1.
b100 1
00
1"
1/
b10000 3
1(
#2924000
b100 1
1.
1%
0&
#2925000
0(
#2950000
b100 1
0.
10
0"
0/
1(
#2974000
b100 1
1$
1&
#2975000
0(
#3000000
1.
b100 1
00
1"
1/
1(
#3024000
10
b100 1
0.
0!
1#
0&
#3025000
0(
#3050000
1(
#3074000
b100 1
0$
1)
0#
#3075000
0(
#3100000
b100 4
b100 2
b0 1
00
0"
0/
b1 3
1(
#3125000
0(
#3150000
1(
#3174000
b10 4
b10 2
0%
1$
#3175000
0(
#3200000
1(
#3224000
1!
0'
1#
1&
#3225000
0(
#3250000
1(
#3274000
0!
0)
1'
#3275000
0(
#3300000
b10000 1
10
b10 3
1(
#3324000
b10000 1
1!
0'
0&
#3325000
0(
#3350000
1+
b10000 1
00
1"
1/
1(
#3374000
b10000 1
1+
1)
1'
0#
1&
#3375000
0(
#3400000
b0 1
0+
0"
0/
b1 3
1(
#3424000
1%
0!
0'
1#
0&
#3425000
0(
#3450000
1(
#3474000
b10000 4
b10000 2
0%
0$
1!
1'
0#
#3475000
0(
#3500000
1(
#3524000
b10 4
b10 2
1$
0'
1&
#3525000
0(
#3550000
1(
#3574000
1%
0!
0)
1#
#3575000
0(
#3600000
b10000 1
10
b10 3
1(
#3624000
b10000 1
1!
0#
#3625000
0(
#3650000
1+
b10000 1
00
1"
1/
1(
#3674000
b10000 1
1+
1)
1'
#3675000
0(
#3700000
b0 1
0+
0"
0/
b1 3
1(
#3724000
b1000 4
b1000 2
0%
0$
0!
0'
1#
#3725000
0(
#3750000
1(
#3774000
b10 4
b10 2
1%
1$
1!
1'
#3775000
0(
#3800000
1(
#3824000
0%
0!
0)
0'
#3825000
0(
#3850000
b10000 1
10
b10 3
1(
#3874000
b10000 4
b10000 2
b10000 1
0$
1)
1'
0#
0&
#3875000
0(
#3900000
b0 1
00
b1 3
1(
#3924000
b10 4
b10 2
1$
0'
1#
1&
#3925000
0(
#3950000
1(
#3974000
b100 4
b100 2
1%
0$
1!
1'
0#
0&
#3975000
0(
#4000000
1(
#4024000
b1000 4
b1000 2
0%
0'
1#
#4025000
0(
#4050000
1(
#4074000
b100 4
b100 2
1%
0!
1'
0#
#4075000
0(
#4100000
1(
#4124000
1!
0'
1#
#4125000
0(
#4150000
1(
#4174000
b10 4
b10 2
1$
0!
0)
0#
1&
#4175000
0(
#4200000
b10000 1
10
b10 3
1(
#4224000
b1000 4
b1000 2
b10000 1
0%
0$
1'
1#
#4225000
0(
#4250000
b10 1
1"
1/
b1000 3
1(
#4274000
b10 4
00
b10 2
1*
b10 1
1%
1$
1!
1)
0'
0#
0&
#4275000
0(
#4300000
b0 1
0*
0"
0/
b1 3
1(
#4324000
b1000 4
b1000 2
0%
0$
0!
0)
1'
1#
1&
#4325000
0(
#4350000
b10 1
10
b1000 3
1(
#4374000
b10000 4
b10000 2
b10 1
1$
1)
0#
0&
#4375000
0(
#4400000
b10 4
b10 2
b0 1
00
b1 3
1(
#4424000
b100 4
b100 2
1%
0$
0)
1#
1&
#4425000
0(
#4450000
b1 1
10
b100 3
1(
#4474000
b10000 4
b10000 2
b1 1
0%
0#
#4475000
0(
#4500000
b100 1
1"
1/
b10000 3
1(
#4524000
b100 1
1$
0&
#4525000
0(
#4550000
1(
#4574000
b100 1
1%
0$
1)
1#
#4575000
0(
#4600000
b100 4
b100 2
b0 1
00
0"
0/
b1 3
1(
#4624000
b10 4
b10 2
1$
1!
0)
1&
#4625000
0(
#4650000
b10000 1
10
b10 3
1(
#4674000
b10000 1
0%
0!
0#
#4675000
0(
#4700000
b10000 1
1"
1/
1(
#4724000
b1000 2
b10000 1
0$
0'
1#
0&
#4725000
0(
#4750000
1(
#4774000
b10 2
b10000 1
1%
1$
1'
#4775000
0(
#4800000
1(
#4824000
b100 4
00
b100 2
1+
b10000 1
0$
1!
1)
1&
#4825000
0(
#4850000
b0 1
0+
0"
0/
b1 3
1(
#4874000
0'
0#
0&
#4875000
0(
#4900000
1(
#4924000
0!
0)
1#
1&
#4925000
0(
#4950000
b1 1
10
b100 3
1(
#4974000
b1000 4
b1000 2
b1 1
0%
1)
#4975000
0(
#5000000
b0 1
00
b1 3
1(
#5024000
b1 4
b1 2
1!
0)
0#
0&
#5025000
0(
#5050000
1(
#5074000
b1000 4
b1000 2
1)
1'
1#
1&
#5075000
0(
#5100000
1(
#5124000
b100 4
b100 2
1%
0!
0#
0&
#5125000
0(
#5150000
1(
#5174000
b1000 4
b1000 2
0%
1#
1&
#5175000
0(
#5200000
1(
#5224000
b10000 4
b10000 2
0)
0#
#5225000
0(
#5250000
b100 1
10
b10000 3
1(
#5274000
b100 4
b100 2
b100 1
1%
1!
1)
0'
1#
0&
#5275000
0(
#5300000
b0 1
00
b1 3
1(
#5324000
b10 4
b10 2
0%
1$
0)
1'
0#
1&
#5325000
0(
#5350000
b10000 1
10
b10 3
1(
#5374000
b1000 4
b1000 2
b10000 1
0$
0!
1#
0&
#5375000
0(
#5400000
b10 1
1"
1/
b1000 3
1(
#5424000
b10 1
1%
1$
1&
#5425000
0(
#5450000
1(
#5474000
00
1*
b10 1
0%
1!
0'
#5475000
0(
#5500000
b10 1
0*
10
0"
0/
1(
#5524000
b10 1
1%
0!
1)
0&
#5525000
0(
#5550000
b10 4
b10 2
b0 1
00
b1 3
1(
#5574000
0%
0)
0#
#5575000
0(
#5600000
b10000 1
10
b10 3
1(
#5624000
b100000 4
b100000 2
b10000 1
0$
1!
1&
#5625000
0(
#5650000
1-
b1000 1
00
1"
1/
b100000 3
1(
#5674000
b1000 1
1-
1%
1$
1)
1'
#5675000
0(
#5700000
b10 4
b10 2
b0 1
0-
0"
0/
b1 3
1(
#5724000
0%
0!
0)
1#
0&
#5725000
0(
#5750000
b10000 1
10
b10 3
1(
#5774000
b100 4
b100 2
b10000 1
1%
0$
1!
1)
1&
#5775000
0(
#5800000
b0 1
00
b1 3
1(
#5824000
b1000 4
b1000 2
0%
0'
0&
#5825000
0(
#5850000
1(
#5874000
b100 4
b100 2
1%
0!
1'
0#
#5875000
0(
#5900000
1(
#5924000
b1000 4
b1000 2
0%
1#
1&
#5925000
0(
#5950000
1(
#5974000
b100 4
b100 2
1%
1!
0)
0'
0&
#5975000
0(
#6000000
b1 1
10
b100 3
1(
#6024000
b10000 4
b10000 2
b1 1
0%
0!
1'
0#
#6025000
0(
#6050000
b100 1
1"
1/
b10000 3
1(
#6074000
b100 1
1%
1)
1&
#6075000
0(
#6100000
b100 4
b100 2
b0 1
00
0"
0/
b1 3
1(
#6124000
1!
1#
0&
#6125000
0(
#6150000
1(
#6174000
0#
#6175000
0(
#6200000
1(
#6224000
1#
1&
#6225000
0(
#6250000
1(
#6274000
b10 4
b10 2
0%
1$
0!
0'
0#
0&
#6275000
0(
#6300000
1(
#6324000
0)
1&
#6325000
0(
#6350000
b10000 1
10
b10 3
1(
#6374000
b100 4
b100 2
b10000 1
1%
0$
1)
1#
0&
#6375000
0(
#6400000
b0 1
00
b1 3
1(
#6424000
1!
0#
1&
#6425000
0(
#6450000
1(
#6474000
b1000 4
b1000 2
0%
0)
1'
1#
#6475000
0(
#6500000
b10 1
10
b1000 3
1(
#6524000
b10 1
1%
1)
0'
#6525000
0(
#6550000
b100 4
b100 2
b0 1
00
b1 3
1(
#6574000
b10 4
b10 2
0%
1$
0!
#6575000
0(
#6600000
1(
#6624000
b1 4
b1 2
0$
0)
0#
0&
#6625000
0(
#6650000
1(
#6674000
b1000 4
b1000 2
1)
1'
1#
#6675000
0(
#6700000
1(
#6724000
b10 4
b10 2
1$
1!
0'
1&
#6725000
0(
#6750000
1(
#6774000
b1000 4
b1000 2
0$
0!
0)
1'
0&
#6775000
0(
#6800000
b10 1
10
b1000 3
1(
#6824000
b10000 4
b10000 2
b10 1
1$
1)
0#
1&
#6825000
0(
#6850000
b10 4
b10 2
b0 1
00
b1 3
1(
#6874000
1%
1!
0'
1#
#6875000
0(
#6900000
1(
#6924000
b1000 4
b1000 2
0%
0$
0!
0&
#6925000
0(
#6950000
1(
#6974000
b100 4
b100 2
1%
#6975000
0(
#7000000
1(
#7024000
b10 4
b10 2
1$
1!
0)
1'
1&
#7025000
0(
#7050000
b10000 1
10
b10 3
1(
#7074000
b100 4
b100 2
b10000 1
0$
1)
0#
0&
#7075000
0(
#7100000
b0 1
00
b1 3
1(
#7124000
0!
0'
1&
#7125000
0(
#7150000
1(
#7174000
b100000 4
b100000 2
0%
#7175000
0(
#7200000
1(
#7224000
b10 4
b10 2
1$
1!
1'
1#
#7225000
0(
#7250000
1(
#7274000
b100 4
b100 2
1%
0$
0)
0#
#7275000
0(
#7300000
b1 1
10
b100 3
1(
#7324000
b1000 4
b1000 2
b1 1
0%
1$
0!
1)
0'
1#
0&
#7325000
0(
#7350000
b10 4
b10 2
b0 1
00
b1 3
1(
#7374000
1%
0)
1'
0#
#7375000
0(
#7400000
b10000 1
10
b10 3
1(
#7424000
b10000 1
0%
1!
1#
1&
#7425000
0(
#7450000
1+
b10000 1
00
1"
1/
1(
#7474000
b10000 1
1+
1%
1)
0#
#7475000
0(
#7500000
b0 1
0+
0"
0/
b1 3
1(
#7524000
0'
1#
0&
#7525000
0(
#7550000
1(
#7574000
b1000 4
b1000 2
0%
0$
1'
#7575000
0(
#7600000
1(
#7624000
b100 4
b100 2
1%
0!
0)
#7625000
0(
#7650000
b1 1
10
b100 3
1(
#7674000
b1000 4
b1000 2
b1 1
0%
1!
0'
1&
#7675000
0(
#7700000
1*
b10 1
00
1"
1/
b1000 3
1(
#7724000
b10 4
b10 2
b10 1
1*
1$
0#
0&
#7725000
0(
#7750000
b10000 1
0*
10
0"
0/
b10 3
1(
#7774000
b10000 1
1%
#7775000
0(
#7800000
1+
b10000 1
00
1"
1/
1(
#7824000
10
b100 2
b10000 1
0+
0$
0!
1#
1&
#7825000
0(
#7850000
1(
#7874000
b1000 2
b10000 1
0%
1)
1'
#7875000
0(
#7900000
b0 1
00
b1000 4
0"
0/
b1 3
1(
#7924000
b100 4
b100 2
1%
1!
0)
0'
0#
#7925000
0(
#7950000
b1 1
10
b100 3
1(
#7974000
b1 1
0!
1'
1#
#7975000
0(
#8000000
b1 1
1"
1/
1(
#8024000
b1000 2
b1 1
0%
0'
#8025000
0(
#8050000
1(
#8074000
b100 2
b1 1
1%
1'
#8075000
0(
#8100000
1(
#8124000
00
1,
b1 1
1$
1!
1)
0'
0&
#8125000
0(
#8150000
b10 4
b10 2
b0 1
0,
0"
0/
b1 3
1(
#8174000
0%
0!
0)
1'
#8175000
0(
#8200000
b10000 1
10
b10 3
1(
#8224000
b10000 1
0#
#8225000
0(
#8250000
b10000 1
1"
1/
1(
#8274000
b100 4
00
b100 2
1+
b10000 1
1%
0$
1!
1#
1&
#8275000
0(
#8300000
b1 1
0+
10
0"
0/
b100 3
1(
#8324000
b1000 4
b1000 2
b1 1
0%
0!
0'
#8325000
0(
#8350000
b10 1
1"
1/
b1000 3
1(
#8374000
b10000 4
00
b10000 2
1*
b10 1
1%
1$
1!
1)
1'
0#
0&
#8375000
0(
#8400000
b10 4
b10 2
b0 1
0*
0"
0/
b1 3
1(
#8424000
0)
0'
1#
1&
#8425000
0(
#8450000
b10000 1
10
b10 3
1(
#8474000
b100 4
b100 2
b10000 1
0$
1'
0&
#8475000
0(
#8500000
1,
b1 1
00
1"
1/
b100 3
1(
#8524000
10
b1 1
0,
1$
0!
1)
0'
1&
#8525000
0(
#8550000
b10 4
b10 2
b0 1
00
0"
0/
b1 3
1(
#8574000
b1 4
b1 2
0%
0$
0#
0&
#8575000
0(
#8600000
1(
#8624000
b100 4
b100 2
1%
0)
1'
#8625000
0(
#8650000
b1 1
10
b100 3
1(
#8674000
b1000 4
b1000 2
b1 1
0%
1!
1#
#8675000
0(
#8700000
1*
b10 1
00
1"
1/
b1000 3
1(
#8724000
b10000 4
b10000 2
b10 1
1*
1$
1)
0#
#8725000
0(
#8750000
b10 4
b10 2
b0 1
0*
0"
0/
b1 3
1(
#8774000
0'
1#
#8775000
0(
#8800000
1(
#8824000
1%
1&
#8825000
0(
#8850000
1(
#8874000
0%
0#
0&
#8875000
0(
#8900000
1(
#8924000
b100000 4
b100000 2
0$
1&
#8925000
0(
#8950000
1(
#8974000
b10 4
b10 2
1$
0)
1'
#8975000
0(
#9000000
b10000 1
10
b10 3
1(
#9024000
b100 4
b100 2
b10000 1
1%
0$
0!
1#
#9025000
0(
#9050000
b1 1
1"
1/
b100 3
1(
#9074000
b10000 2
b1 1
0%
1$
0#
0&
#9075000
0(
#9100000
1(
#9124000
b100 2
b1 1
1%
0$
1#
#9125000
0(
#9150000
1(
#9174000
b10000 2
b1 1
0%
1$
1)
0#
1&
#9175000
0(
#9200000
b10 2
b0 1
00
b10 4
0"
0/
b1 3
1(
#9224000
1!
0)
1#
#9225000
0(
#9250000
b10000 1
10
b10 3
1(
#9274000
b10000 1
1%
0!
0#
#9275000
0(
#9300000
b10000 1
1"
1/
1(
#9324000
00
1+
b10000 1
1!
0'
1#
#9325000
0(
#9350000
b10000 1
0+
10
0"
0/
1(
#9374000
b10000 1
0!
1)
1'
0#
0&
#9375000
0(
#9400000
b0 1
00
b1 3
1(
#9424000
b1000 4
b1000 2
0%
0$
0'
1#
1&
#9425000
0(
#9450000
1(
#9474000
b10 4
b10 2
1$
0#
#9475000
0(
#9500000
1(
#9524000
b100 4
b100 2
1%
0$
0)
1'
0&
#9525000
0(
#9550000
b1 1
10
b100 3
1(
#9574000
b10000 4
b10000 2
b1 1
0%
1)
1&
#9575000
0(
#9600000
b0 1
00
b1 3
1(
#9624000
b10 4
b10 2
1$
#9625000
0(
#9650000
1(
#9674000
1!
0)
#9675000
0(
#9700000
b10000 1
10
b10 3
1(
#9724000
b10000 1
0!
1)
0'
1#
#9725000
0(
#9750000
b0 1
00
b1 3
1(
#9774000
0)
0&
#9775000
0(
#9800000
b10000 1
10
b10 3
1(
#9824000
b100 4
b100 2
b10000 1
1%
0$
0#
#9825000
0(
#9850000
b1 1
1"
1/
b100 3
1(
#9874000
00
1,
b1 1
1!
1#
1&
#9875000
0(
#9900000
b1 1
0,
10
0"
0/
1(
#9924000
b1000 4
b1000 2
b1 1
0%
0!
1)
1'
#9925000
0(
#9950000
b0 1
00
b1 3
1(
#9974000
b10 4
b10 2
1$
1!
0#
0&
#9975000
0(
#10000000
1(
#10024000
b100 4
b100 2
1%
0$
#10025000
0(
#10050000
1(
#10074000
b1000 4
b1000 2
0%
0!
0)
0'
1#
#10075000
0(
#10100000
b10 1
10
b1000 3
1(
#10124000
b10 4
b10 2
b10 1
1%
1$
0#
#10125000
0(
#10150000
b10000 1
1"
1/
b10 3
1(
#10174000
b10000 1
1'
1#
1&
#10175000
0(
#10200000
1(
#10224000
b1000 2
b10000 1
0%
0$
1)
0'
0&
#10225000
0(
#10250000
b0 1
00
b1000 4
0"
0/
b1 3
1(
#10274000
b10 4
b10 2
1%
1$
1'
#10275000
0(
#10300000
1(
#10324000
0)
0'
#10325000
0(
#10350000
b10000 1
10
b10 3
1(
#10374000
b10000 1
1!
1)
1'
0#
#10375000
0(
#10400000
b0 1
00
b1 3
1(
#10424000
b100 4
b100 2
0$
0'
#10425000
0(
#10450000
1(
#10474000
b10 4
b10 2
0%
1$
0!
1'
1#
#10475000
0(
#10500000
1(
#10524000
1%
0'
0#
#10525000
0(
#10550000
1(
#10574000
b100 4
b100 2
0$
1!
#10575000
0(
#10600000
1(
#10624000
b10 4
b10 2
1$
0)
1'
1#
#10625000
0(
#10650000
b10000 1
10
b10 3
1(
#10674000
b100 4
b100 2
b10000 1
0$
1)
#10675000
0(
#10700000
b0 1
00
b1 3
1(
#10724000
b10 4
b10 2
1$
0!
1&
#10725000
0(
#10750000
1(
#10774000
0%
1!
0)
0#
#10775000
0(
#10800000
b10000 1
10
b10 3
1(
#10824000
b10000 1
0!
0'
#10825000
0(
#10850000
b10000 1
1"
1/
1(
#10874000
b100 2
b10000 1
1%
0$
1)
1'
#10875000
0(
#10900000
b0 1
00
b100 4
0"
0/
b1 3
1(
#10924000
1!
1#
0&
#10925000
0(
#10950000
1(
#10974000
b10 4
b10 2
0%
1$
0)
0#
1&
#10975000
0(
#11000000
b10000 1
10
b10 3
1(
#11024000
b1000 4
b1000 2
b10000 1
0$
0'
1#
#11025000
0(
#11050000
1*
b10 1
00
1"
1/
b1000 3
1(
#11074000
b10000 4
b10000 2
b10 1
1*
1)
1'
0#
0&
#11075000
0(
#11100000
b0 1
0*
0"
0/
b1 3
1(
#11124000
b100000 4
b100000 2
0)
0'
1&
#11125000
0(
#11150000
b1000 1
10
b100000 3
1(
#11174000
b1000 1
1%
#11175000
0(
#11200000
1-
b1000 1
00
1"
1/
1(
