APB/ABP_goldminer_result/verilog/APB/APB.v


`timescale 1ns/1ps //timescale 

module APB(
			//standard ARM
	    	input PCLK,
			input PRESETn,
			input PSELx,
			input PWRITE,
			input PENABLE,
			input [31:0] PADDR,
			input [31:0] PWDATA,

			//internal pin
			input [31:0] READ_DATA_ON_RX,
			input ERROR,
			input TX_EMPTY,
			input RX_EMPTY,
			
			//external pin
			output [31:0] PRDATA,

			//internal pin 
			output reg [13:0] INTERNAL_I2C_REGISTER_CONFIG,
			output reg [13:0] INTERNAL_I2C_REGISTER_TIMEOUT,
			output [31:0] WRITE_DATA_ON_TX,
			output  WR_ENA,
			output  RD_ENA,
			
			//outside port 
			output PREADY,
			output PSLVERR,

			//interruption
			output INT_RX,
			output INT_TX
	   

	  );

//ENABLE WRITE ON TX FIFO
assign WR_ENA = (PWRITE == 1'b1 & PENABLE == 1'b1 & PADDR == 32'd0 & PSELx == 1'b1)?  1'b1:1'b0;

//ENABLE READ ON RX FIFO
assign RD_ENA = (PWRITE == 1'b0 & PENABLE == 1'b1  & PADDR == 32'd4 & PSELx == 1'b1)?  1'b1:1'b0;

//WRITE ON I2C MODULE
assign PREADY = ((WR_ENA == 1'b1 | RD_ENA == 1'b1 | PADDR == 32'd8 | PADDR == 32'd12) &  (PENABLE == 1'b1 & PSELx == 1'b1))? 1'b1:1'b0;

//INPUT TO WRITE ON TX FIFO
assign WRITE_DATA_ON_TX = (PADDR == 32'd0)? PWDATA:PWDATA;

//OUTPUT DATA FROM RX TO PRDATA
assign PRDATA = (PADDR == 32'd4)? READ_DATA_ON_RX:READ_DATA_ON_RX;

//ERROR FROM I2C CORE
assign PSLVERR = ERROR; 

//INTERRUPTION FROM I2C
assign INT_TX = TX_EMPTY;

//INTERRUPTION FROM I2C
assign INT_RX = RX_EMPTY;

//This is sequential logic used only to register configuration
always@(posedge PCLK)
begin

	if(!PRESETn)
	begin
		INTERNAL_I2C_REGISTER_CONFIG <= 14'd0;
		INTERNAL_I2C_REGISTER_TIMEOUT <= 14'd0;
	end
	else
	begin

		// Set configuration to i2c
		if(PADDR == 32'd8 && PSELx == 1'b1 && PWRITE == 1'b1 && PREADY == 1'b1)
		begin
			INTERNAL_I2C_REGISTER_CONFIG <= PWDATA[13:0];
		end
		else if(PADDR == 32'd12 && PSELx == 1'b1 && PWRITE == 1'b1 && PREADY == 1'b1)
		begin
			INTERNAL_I2C_REGISTER_TIMEOUT <= PWDATA[13:0];
		end
		else
		begin
			INTERNAL_I2C_REGISTER_CONFIG <= INTERNAL_I2C_REGISTER_CONFIG;
		end
		
	end

end 


endmodule

APB/ABP_goldminer_result/RunTime/goldmine.out/APB/APB_bench.v
`timescale 1ns/1ps

module APB_bench();

reg DEFAULT_RESET;
reg [31:0] PWDATA;
reg PWRITE;
reg PSELx;
reg RX_EMPTY;
reg PCLK;
reg PENABLE;
reg [31:0] PADDR;
reg [31:0] READ_DATA_ON_RX;
reg PRESETn;
reg ERROR;
reg TX_EMPTY;

wire PREADY;
wire [31:0] WRITE_DATA_ON_TX;
wire [31:0] PRDATA;
wire INT_RX;
wire [13:0] INTERNAL_I2C_REGISTER_TIMEOUT;
wire RD_ENA;
wire WR_ENA;
wire [13:0] INTERNAL_I2C_REGISTER_CONFIG;
wire PSLVERR;
wire INT_TX;

APB APB_ (
	.PWDATA(PWDATA),
	.PWRITE(PWRITE),
	.PSELx(PSELx),
	.RX_EMPTY(RX_EMPTY),
	.PCLK(PCLK),
	.PENABLE(PENABLE),
	.PADDR(PADDR),
	.READ_DATA_ON_RX(READ_DATA_ON_RX),
	.PRESETn(PRESETn),
	.ERROR(ERROR),
	.TX_EMPTY(TX_EMPTY),
	.PREADY(PREADY),
	.WRITE_DATA_ON_TX(WRITE_DATA_ON_TX),
	.PRDATA(PRDATA),
	.INT_RX(INT_RX),
	.INTERNAL_I2C_REGISTER_TIMEOUT(INTERNAL_I2C_REGISTER_TIMEOUT),
	.RD_ENA(RD_ENA),
	.WR_ENA(WR_ENA),
	.INTERNAL_I2C_REGISTER_CONFIG(INTERNAL_I2C_REGISTER_CONFIG),
	.PSLVERR(PSLVERR),
	.INT_TX(INT_TX));

	initial begin
		$dumpfile("/home/hrostami/ABP_goldminer/RunTime/goldmine.out/APB/APB.vcd");
		$dumpvars(0, APB_bench.APB_);
		PCLK = 1;
		DEFAULT_RESET = 1;
		#26;
		DEFAULT_RESET = 0;
		#186300 $finish;
	end

	always begin
		#25 PCLK = ~PCLK;
	end

	always begin
		#24;
		PWDATA = $random;
		PWRITE = $random;
		PSELx = $random;
		RX_EMPTY = $random;
		PENABLE = $random;
		PADDR = $random;
		READ_DATA_ON_RX = $random;
		PRESETn = $random;
		ERROR = $random;
		TX_EMPTY = $random;
		#26;
	end

endmodule

APB/ABP_goldminer_result/RunTime/goldmine.out/APB/APB.vcd
$date
	Fri Jun 16 13:32:45 2023
$end
$version
	Icarus Verilog
$end
$timescale
	1ps
$end
$scope module APB_bench $end
$scope module APB_ $end
$var wire 1 ! ERROR $end
$var wire 1 " INT_RX $end
$var wire 1 # INT_TX $end
$var wire 32 $ PADDR [31:0] $end
$var wire 1 % PCLK $end
$var wire 1 & PENABLE $end
$var wire 1 ' PRESETn $end
$var wire 1 ( PSELx $end
$var wire 1 ) PSLVERR $end
$var wire 32 * PWDATA [31:0] $end
$var wire 1 + PWRITE $end
$var wire 32 , READ_DATA_ON_RX [31:0] $end
$var wire 1 - RX_EMPTY $end
$var wire 1 . TX_EMPTY $end
$var wire 1 / WR_ENA $end
$var wire 32 0 WRITE_DATA_ON_TX [31:0] $end
$var wire 1 1 RD_ENA $end
$var wire 1 2 PREADY $end
$var wire 32 3 PRDATA [31:0] $end
$var reg 14 4 INTERNAL_I2C_REGISTER_CONFIG [13:0] $end
$var reg 14 5 INTERNAL_I2C_REGISTER_TIMEOUT [13:0] $end
$upscope $end
$upscope $end
$enddefinitions $end
#0
$dumpvars
bx 5
bx 4
bx 3
x2
x1
bx 0
x/
x.
x-
bx ,
x+
bx *
x)
x(
x'
x&
1%
bx $
x#
x"
x!
$end
#24000
02
0/
01
b10110010110000101000010001100101 3
b10010000101010011010100100100 0
1#
1.
1)
1!
0'
b10110010110000101000010001100101 ,
b1000110110111111001100110001101 $
1&
1"
1-
1(
1+
b10010000101010011010100100100 *
#25000
0%
#50000
b0 5
b0 4
1%
#74000
b11100010111101111000010011000101 3
b111011001000111111000101110110 0
b11100010111101111000010011000101 ,
b11100011001101110010010011000110 $
0"
0-
b111011001000111111000101110110 *
#75000
0%
#100000
1%
#124000
b101110010110000100100101011100 3
b10001001001100101101011000010010 0
1'
b101110010110000100100101011100 ,
b11100010110010100100111011000101 $
0&
0(
b10001001001100101101011000010010 *
#125000
0%
#150000
1%
#174000
b11001011001000000011111010010110 3
b10110001111011110110001001100011 0
b11001011001000000011111010010110 ,
b11001110110011001100110010011101 $
0+
b10110001111011110110001001100011 *
#175000
0%
#200000
1%
#224000
b10001100001000100100100100011 3
b110101100111111101110101101011 0
0#
0.
0)
0!
0'
b10001100001000100100100100011 ,
b11100111110001010111001011001111 $
1&
1+
b110101100111111101110101101011 *
#225000
0%
#250000
1%
#274000
b1110101110001010000110111101011 3
b1111001011010001011110111110010 0
b1110101110001010000110111101011 ,
b11000100100010100001001010001001 $
0&
1(
0+
b1111001011010001011110111110010 *
#275000
0%
#300000
1%
#324000
b10011101110011000110000000111011 3
b11011110011101010000001010111100 0
1#
1.
b10011101110011000110000000111011 ,
b100111111100100101010101001111 $
1&
1"
1-
b11011110011101010000001010111100 *
#325000
0%
#350000
1%
#374000
b1111100011011011010100111111000 3
b1111000110110011001101111110001 0
0#
0.
1)
1!
1'
b1111100011011011010100111111000 ,
b1000111101110011010000110001111 $
0"
0-
0(
1+
b1111000110110011001101111110001 *
#375000
0%
#400000
1%
#424000
b1001011001000010010111110010110 3
b10101101110010111100000001011011 0
0)
0!
0'
b1001011001000010010111110010110 ,
b10101000110001111111110001010001 $
1(
b10101101110010111100000001011011 *
#425000
0%
#450000
1%
#474000
b1111110100101000111100011111 3
b10111011100000100101101001110111 0
1)
1!
1'
b1111110100101000111100011111 ,
b11100110110011110011100111001 $
0(
b10111011100000100101101001110111 *
#475000
0%
#500000
1%
#524000
b11000111000110100000110010001110 3
b101101110110100101100101011011 0
0)
0!
0'
b11000111000110100000110010001110 ,
b11000011001111110011100010000110 $
0&
1(
b101101110110100101100101011011 *
#525000
0%
#550000
1%
#574000
b1111011111110001111110111110111 3
b111001100101100001011101110011 0
1'
b1111011111110001111110111110111 ,
b100010001010010000110101000100 $
1&
1"
1-
b111001100101100001011101110011 *
#575000
0%
#600000
1%
#624000
b111100111100010001100101111001 3
b10100110011111100000100101001 0
0'
b111100111100010001100101111001 ,
b11101111101111101001010011011111 $
0(
b10100110011111100000100101001 *
#625000
0%
#650000
1%
#674000
b101011000011101110110101010110 3
b1010101111101101010110110101011 0
1)
1!
b101011000011101110110101010110 ,
b11100001111100010000001011000011 $
0"
0-
0+
b1010101111101101010110110101011 *
#675000
0%
#700000
1%
#724000
b10000010001111110010110000000100 3
b1011011011011111011100110110110 0
1#
1.
1'
b10000010001111110010110000000100 ,
b1001001110001100101110110010011 $
0&
1(
b1011011011011111011100110110110 *
#725000
0%
#750000
1%
#774000
b10100011000001110001101001000110 3
b1101100101100001011011111011001 0
0'
b10100011000001110001101001000110 ,
b1001010100100110111000110010101 $
0(
1+
b1101100101100001011011111011001 *
#775000
0%
#800000
1%
#824000
b10000100011101111110010000001000 3
b11011010011011101011101010110100 0
b10000100011101111110010000001000 ,
b10010111010111001001110000101110 $
1&
1"
1-
0+
b11011010011011101011101010110100 *
#825000
0%
#850000
1%
#874000
b10111001111101010000010001110011 3
b10001110001101111001000000011100 0
0#
0.
0)
0!
b10111001111101010000010001110011 ,
b10111000010101011100010001110000 $
0&
b10001110001101111001000000011100 *
#875000
0%
#900000
1%
#924000
b10011001001011001111100100110 3
b1101010100011100000010111010101 0
1)
1!
b10011001001011001111100100110 ,
b1100000001110010010000111000000 $
1(
b1101010100011100000010111010101 *
#925000
0%
#950000
1%
#974000
b11111101001010001110010011111010 3
b1000011011000010101011110000110 0
1#
1.
1'
b11111101001010001110010011111010 ,
b111100111011010010101101111001 $
1&
0(
b1000011011000010101011110000110 *
#975000
0%
#1000000
1%
#1024000
b11100010111001010111010011000101 3
b1000011011101111001000110000110 0
0'
b11100010111001010111010011000101 ,
b1100000101100010111010111000001 $
1(
b1000011011101111001000110000110 *
#1025000
0%
#1050000
1%
#1074000
b111000010111011100100001110 3
b11110110001000101110011011101100 0
0#
0.
b111000010111011100100001110 ,
b11010000110010101000110010100001 $
0"
0-
0(
b11110110001000101110011011101100 *
#1075000
0%
#1100000
1%
#1124000
b1100101001000110100010111001010 3
b10101010110100001110100101010 0
1#
1.
1'
b1100101001000110100010111001010 ,
b1100100011001001110001111001000 $
1+
b10101010110100001110100101010 *
#1125000
0%
#1150000
1%
#1174000
b111111101110110011101101111111 3
b1011011000010111101110110110110 0
0#
0.
0)
0!
0'
b111111101110110011101101111111 ,
b11011010001001101001101010110100 $
0&
1"
1-
0+
b1011011000010111101110110110110 *
#1175000
0%
#1200000
1%
#1224000
b11010000100101011010100010100001 3
b11001010001010010000100110010 0
1#
1.
1)
1!
b11010000100101011010100010100001 ,
b1010100101010000111100110101001 $
0"
0-
1+
b11001010001010010000100110010 *
#1225000
0%
#1250000
1%
#1274000
b1000100011001011110011110001000 3
b11110111100000101001000011101111 0
0#
0.
b1000100011001011110011110001000 ,
b110101110011011011111101101011 $
1&
1"
1-
b11110111100000101001000011101111 *
#1275000
0%
#1300000
1%
#1324000
b1110110011110011111110111101100 3
b10100010001001101111100101000 0
b1110110011110011111110111101100 ,
b110101100110000010100001101 $
0&
0"
0-
1(
b10100010001001101111100101000 *
#1325000
0%
#1350000
1%
#1374000
b11110001011001101111101011100010 3
b10100000110000000010010001000001 0
b11110001011001101111101011100010 ,
b10101101101011000010001001011011 $
1"
1-
0(
b10100000110000000010010001000001 *
#1375000
0%
#1400000
1%
#1424000
b1000000100100000101110110000001 3
b1001001111100100110100010010 0
1#
1.
b1000000100100000101110110000001 ,
b10101100010010000111100101011 $
1&
1(
0+
b1001001111100100110100010010 *
#1425000
0%
#1450000
1%
#1474000
b11001011001000100111000010010110 3
b10001111100011000110111000011111 0
1'
b11001011001000100111000010010110 ,
b10001001000110011011010000010010 $
0&
0"
0-
0(
b10001111100011000110111000011111 *
#1475000
0%
#1500000
1%
#1524000
b11110011110101111010011011100111 3
b10101100010110010101100101011 0
b11110011110101111010011011100111 ,
b11010011101010001110010010100111 $
1"
1-
1(
1+
b10101100010110010101100101011 *
#1525000
0%
#1550000
1%
#1574000
b1000001101000010000010110000011 3
b1100100101110100000111111001001 0
0#
0.
0)
0!
0'
b1000001101000010000010110000011 ,
b10100010111001100010000001000101 $
0"
0-
b1100100101110100000111111001001 *
#1575000
0%
#1600000
1%
#1624000
b10010100000010010111011000101000 3
b10110100010101011111001001101000 0
1)
1!
b10010100000010010111011000101000 ,
b100000011101101001000101000000 $
0(
b10110100010101011111001001101000 *
#1625000
0%
#1650000
1%
#1674000
b1010111011000011010100010101 3
b111010011000100101111101110100 0
1#
1.
1'
b1010111011000011010100010101 ,
b110001001001001101001101100010 $
b111010011000100101111101110100 *
#1675000
0%
#1700000
1%
#1724000
b11110101100010011100000111 3
b1100100101101011110001111001001 0
0)
0!
0'
b11110101100010011100000111 ,
b10101101011001111110001001011010 $
1&
1"
1-
1(
0+
b1100100101101011110001111001001 *
#1725000
0%
#1750000
1%
#1774000
b10010000001010100011101000100000 3
b10011101111000010111110000111011 0
0#
0.
b10010000001010100011101000100000 ,
b101010101110001111011101010101 $
0&
0"
0-
b10011101111000010111110000111011 *
#1775000
0%
#1800000
1%
#1824000
b10111101111000001101001001111011 3
b1101110100010101111010111011101 0
1#
1.
1)
1!
1'
b10111101111000001101001001111011 ,
b11111110111100000110010011111101 $
1"
1-
1+
b1101110100010101111010111011101 *
#1825000
0%
#1850000
1%
#1874000
b101001011110100001010101010010 3
b1110100100100100001100011101 0
0#
0.
0'
b101001011110100001010101010010 ,
b11110110101000010111100011101101 $
0(
b1110100100100100001100011101 *
#1875000
0%
#1900000
1%
#1924000
b1000010011110110101011110000100 3
b1000010000110011110011110000100 0
0)
0!
b1000010011110110101011110000100 ,
b110101001011010110000101101010 $
1&
0"
0-
0+
b1000010000110011110011110000100 *
#1925000
0%
#1950000
1%
#1974000
b10100100100011110111110001001001 3
b1011101010010100100110110111010 0
1#
1.
1)
1!
b10100100100011110111110001001001 ,
b11010001000001010000010010100010 $
0&
1"
1-
1+
b1011101010010100100110110111010 *
#1975000
0%
#2000000
1%
#2024000
b10010110001000100101000000101100 3
b10101110011010000011000001011100 0
0#
0.
b10010110001000100101000000101100 ,
b1101000010100011110010111010000 $
b10101110011010000011000001011100 *
#2025000
0%
#2050000
1%
#2074000
b1010010000011101110111110100100 3
b1000100101011111100100010001 0
1#
1.
1'
b1010010000011101110111110100100 ,
b10001111111100000010100100011 $
1(
0+
b1000100101011111100100010001 *
#2075000
0%
#2100000
1%
#2124000
b11101100101110010001101011011001 3
b11101010010110000001010011010100 0
0)
0!
0'
b11101100101110010001101011011001 ,
b100100110100101011111101001001 $
0"
0-
1+
b11101010010110000001010011010100 *
#2125000
0%
#2150000
1%
#2174000
b10010101101010011010100000101011 3
b1110001101101000110000111100011 0
0#
0.
1'
b10010101101010011010100000101011 ,
b1000010001001101010100110000100 $
1"
1-
0(
0+
b1110001101101000110000111100011 *
#2175000
0%
#2200000
1%
#2224000
b1011101100001011101001110111011 3
b101100100001001000100101011001 0
1#
1.
1)
1!
0'
b1011101100001011101001110111011 ,
b1010011010100100111011110100110 $
1&
b101100100001001000100101011001 *
#2225000
0%
#2250000
1%
#2274000
b10110100111110011010010001101001 3
b10000110010100110110001000001100 0
0#
0.
0)
0!
1'
b10110100111110011010010001101001 ,
b10101000111001001101100001010001 $
0&
1(
1+
b10000110010100110110001000001100 *
#2275000
0%
#2300000
1%
#2324000
b111011111011010101001101110111 3
b1001101110111010100110110011011 0
1#
1.
b111011111011010101001101110111 ,
b10011000010011010101101000110000 $
0(
0+
b1001101110111010100110110011011 *
#2325000
0%
#2350000
1%
#2374000
b1100001000111011001111111000010 3
b111011000010111001011101110110 0
b1100001000111011001111111000010 ,
b11000000011101100100001010000000 $
1&
1(
1+
b111011000010111001011101110110 *
#2375000
0%
#2400000
1%
#2424000
b1110000111011110011011111100001 3
b10110011000000101101101001100110 0
0#
0.
b1110000111011110011011111100001 ,
b11110111100001010111011011101111 $
0&
0"
0-
b10110011000000101101101001100110 *
#2425000
0%
#2450000
1%
#2474000
b110111000101010001010101101110 3
b11110010100111000101111011100101 0
1)
1!
b110111000101010001010101101110 ,
b10111011101111000101001001110111 $
1&
1"
1-
0(
0+
b11110010100111000101111011100101 *
#2475000
0%
#2500000
1%
#2524000
b11110001011000011101110011100010 3
b1111000011000100111000111110000 0
1#
1.
0'
b11110001011000011101110011100010 ,
b1000111001011101001010110001110 $
1(
b1111000011000100111000111110000 *
#2525000
0%
#2550000
1%
#2574000
b110010110111000100000101100101 3
b10101101111001111101000001011011 0
1'
b110010110111000100000101100101 ,
b1001110010000011010100010011 $
0(
1+
b10101101111001111101000001011011 *
#2575000
0%
#2600000
1%
#2624000
b101100111011100101111101011001 3
b10011101000100100000100000111010 0
b101100111011100101111101011001 ,
b10111110110110100100010001111101 $
0&
0"
0-
b10011101000100100000100000111010 *
#2625000
0%
#2650000
1%
#2674000
b11010001010010000010000010100010 3
b10100000101011101100110001000001 0
0#
0.
0)
0!
b11010001010010000010000010100010 ,
b10000011001001101101010000000110 $
1"
1-
1(
b10100000101011101100110001000001 *
#2675000
0%
#2700000
1%
#2724000
b10001110011001001101100100011 3
b10101000011011000101111001010000 0
1#
1.
b10001110011001001101100100011 ,
b10101110001000111100111001011100 $
0"
0-
b10101000011011000101111001010000 *
#2725000
0%
#2750000
1%
#2774000
b1011100101000100110111110111001 3
b10000111000011001110111000001110 0
b1011100101000100110111110111001 ,
b10101100111011001101110001011001 $
0(
b10000111000011001110111000001110 *
#2775000
0%
#2800000
1%
#2824000
b1001111110010100100000010 3
b110011011001111000100001100 0
0'
b1001111110010100100000010 ,
b100111000111000100001101001110 $
1&
1"
1-
b110011011001111000100001100 *
#2825000
0%
#2850000
1%
#2874000
b10100000000001011010011001000000 3
b11010111101101001000111010101111 0
0#
0.
1)
1!
1'
b10100000000001011010011001000000 ,
b111101100000101011110101111011 $
0&
0+
b11010111101101001000111010101111 *
#2875000
0%
#2900000
1%
#2924000
b11010000110011110110101010100001 3
b10110110010111111100100101101 0
1#
1.
b11010000110011110110101010100001 ,
b101000011101100110100101010000 $
0"
0-
1+
b10110110010111111100100101101 *
#2925000
0%
#2950000
1%
#2974000
b11111101011110010000011011111010 3
b10101110111010101100110001011101 0
0'
b11111101011110010000011011111010 ,
b11001111001100001001110010011110 $
0+
b10101110111010101100110001011101 *
#2975000
0%
#3000000
1%
#3024000
b10110100010010010111011001101000 3
b10101010110110100111010001010101 0
0#
0.
0)
0!
b10110100010010010111011001101000 ,
b10010011011100101100111000100110 $
1&
1"
1-
1(
1+
b10101010110110100111010001010101 *
#3025000
0%
#3050000
1%
#3074000
b10100010110011001000100001000101 3
b1110010000111000010100011100 0
1)
1!
1'
b10100010110011001000100001000101 ,
b1101100011010100110110111011000 $
0"
0-
b1110010000111000010100011100 *
#3075000
0%
#3100000
1%
#3124000
b10101100011110000010110001011000 3
b1101110000111100001111111011100 0
0)
0!
0'
b10101100011110000010110001011000 ,
b11111001100010111100000011110011 $
0&
1"
1-
0+
b1101110000111100001111111011100 *
#3125000
0%
#3150000
1%
#3174000
b1011001001101001110100110110010 3
b11001101000111010101000010011010 0
1#
1.
1)
1!
b1011001001101001110100110110010 ,
b1100001110110111101010111000011 $
0"
0-
b11001101000111010101000010011010 *
#3175000
0%
#3200000
1%
#3224000
b11010110101000010010100010101101 3
b1110101101011010111001111101011 0
b11010110101000010010100010101101 ,
b1101111000010100101100011011 $
1&
1"
1-
0(
b1110101101011010111001111101011 *
#3225000
0%
#3250000
1%
#3274000
b101011101001111010010101010111 3
b1010101110111011000110110101011 0
0)
0!
b101011101001111010010101010111 ,
b10000010001101000100001000000100 $
0&
1+
b1010101110111011000110110101011 *
#3275000
0%
#3300000
1%
#3324000
b10111000110000001100001001110001 3
b11110010010010111010111011100100 0
0#
0.
1'
b10111000110000001100001001110001 ,
b1000110011001010011011110001100 $
0"
0-
0+
b11110010010010111010111011100100 *
#3325000
0%
#3350000
1%
#3374000
b11011111111101101111011010111111 3
b1011111011000101011100010111 0
1)
1!
0'
b11011111111101101111011010111111 ,
b11000111101100101110001010001111 $
1&
1"
1-
1(
1+
b1011111011000101011100010111 *
#3375000
0%
#3400000
1%
#3424000
b1100110100001100001110111001101 3
b11000001010001001100110010000010 0
0)
0!
1'
b1100110100001100001110111001101 ,
b11111000110001110001010011110001 $
0&
0+
b11000001010001001100110010000010 *
#3425000
0%
#3450000
1%
#3474000
b11111110101011011101110011111101 3
b11110110011100001000100011101100 0
0'
b11111110101011011101110011111101 ,
b11111111011100101001111011111110 $
1&
b11110110011100001000100011101100 *
#3475000
0%
#3500000
1%
#3524000
b11011000011110000110100110110 3
b1011000000010011000100110110000 0
1#
1.
1)
1!
1'
b11011000011110000110100110110 ,
b11111111001000000010111011111110 $
0"
0-
0(
b1011000000010011000100110110000 *
#3525000
0%
#3550000
1%
#3574000
b11100101101011000001000011001011 3
b1011110010111011111100010111 0
0#
0.
0)
0!
b11100101101011000001000011001011 ,
b11101010011101100010011011010100 $
0&
1+
b1011110010111011111100010111 *
#3575000
0%
#3600000
1%
#3624000
b10100011011001000011001001000110 3
b1000110100010110110000110001101 0
1)
1!
0'
b10100011011001000011001001000110 ,
b10110000010111111000111001100000 $
1&
1"
1-
1(
b1000110100010110110000110001101 *
#3625000
0%
#3650000
1%
#3674000
b100001100000100000111101000011 3
b111001110101100101011101110011 0
1#
1.
b100001100000100000111101000011 ,
b11100111110010100000000 $
0&
0"
0-
0(
0+
b111001110101100101011101110011 *
#3675000
0%
#3700000
1%
#3724000
b10110101101101001110100001101011 3
b1001100010110001000111110011000 0
0#
0.
0)
0!
1'
b10110101101101001110100001101011 ,
b10111000011101100000001001110000 $
1&
1(
1+
b1001100010110001000111110011000 *
#3725000
0%
#3750000
1%
#3774000
b1001100011010001010100010011 3
b110110110110110101100001101 0
1)
1!
b1001100011010001010100010011 ,
b11000000011000100000001010000000 $
0&
0(
b110110110110110101100001101 *
#3775000
0%
#3800000
1%
#3824000
b10001010100110100110100100010 3
b10111100011110000001000001111000 0
b10001010100110100110100100010 ,
b11100010000100001011100111000 $
1&
1"
1-
1(
b10111100011110000001000001111000 *
#3825000
0%
#3850000
1%
#3874000
b1011010110100110001110110110101 3
b1100111010101001101011111001110 0
0)
0!
0'
b1011010110100110001110110110101 ,
b111010110000100110111101110101 $
0&
0(
b1100111010101001101011111001110 *
#3875000
0%
#3900000
1%
#3924000
b11011100000011100100000110 3
b10101100000001011010000001011000 0
1)
1!
b11011100000011100100000110 ,
b1110101001111000001011111101010 $
1&
0"
0-
1(
0+
b10101100000001011010000001011000 *
#3925000
0%
#3950000
1%
#3974000
b1001101100111101110001110011011 3
b100100011001110011100101001000 0
1#
1.
0)
0!
1'
b1001101100111101110001110011011 ,
b1000001101011101101010110000011 $
1"
1-
0(
1+
b100100011001110011100101001000 *
#3975000
0%
#4000000
1%
#4024000
b10101100100101110100100001011001 3
b100111100011011011101101001111 0
1)
1!
b10101100100101110100100001011001 ,
b110000111000100000111101100001 $
0&
0+
b100111100011011011101101001111 *
#4025000
0%
#4050000
1%
#4074000
b1100001110110111110010111000011 3
b11101111000111011110101011011110 0
0#
0.
0)
0!
0'
b1100001110110111110010111000011 ,
b1101010101001001010000111010101 $
1+
b11101111000111011110101011011110 *
#4075000
0%
#4100000
1%
#4124000
b100010111010101101101101000101 3
b1101011001010011001110111010110 0
1#
1.
1)
1!
1'
b100010111010101101101101000101 ,
b1011111111000111100101110111111 $
0"
0-
1(
b1101011001010011001110111010110 *
#4125000
0%
#4150000
1%
#4174000
b11011110001100100101110010111100 3
b11111100011001110000101011111000 0
0)
0!
b11011110001100100101110010111100 ,
b11001110000100001111111010011100 $
1&
0(
0+
b11111100011001110000101011111000 *
#4175000
0%
#4200000
1%
#4224000
b1001101001000000000100110011010 3
b11011001010110110100000010110010 0
b1001101001000000000100110011010 ,
b1100001000011101101010111000010 $
0&
1(
b11011001010110110100000010110010 *
#4225000
0%
#4250000
1%
#4274000
b10111101111000110100100001111011 3
b11000101110011110111001010001011 0
0#
0.
1)
1!
b10111101111000110100100001111011 ,
b110000100111001101101101100001 $
1"
1-
0(
b11000101110011110111001010001011 *
#4275000
0%
#4300000
1%
#4324000
b10010001110101010111100100100 3
b101100101010010110001101011001 0
1#
1.
b10010001110101010111100100100 ,
b1110011111110100111110111100111 $
1&
b101100101010010110001101011001 *
#4325000
0%
#4350000
1%
#4374000
b10001001011001000110000000010010 3
b1001010111111101011111110010101 0
0#
0.
0'
b10001001011001000110000000010010 ,
b10001110001110000100000100 $
0"
0-
1(
1+
b1001010111111101011111110010101 *
#4375000
0%
#4400000
1%
#4424000
b111010000010010110101101110100 3
b11111111110111000000100111111 0
0)
0!
1'
b111010000010010110101101110100 ,
b11111111011100111100101011111110 $
0&
0+
b11111111110111000000100111111 *
#4425000
0%
#4450000
1%
#4474000
b1010101101111000010011110101011 3
b11101111111100110100110011011111 0
1#
1.
0'
b1010101101111000010011110101011 ,
b1011110111010010111101110111101 $
b11101111111100110100110011011111 *
#4475000
0%
#4500000
1%
#4524000
b11010011000011001100100110100 3
b10001001101101011101010000010011 0
0#
0.
1'
b11010011000011001100100110100 ,
b10111101010011000110100101111 $
1&
1"
1-
b10001001101101011101010000010011 *
#4525000
0%
#4550000
1%
#4574000
b11100110100111011101000011001101 3
b11010011111111100011011010100111 0
1)
1!
b11100110100111011101000011001101 ,
b11111101010100101101100011111010 $
0(
1+
b11010011111111100011011010100111 *
#4575000
0%
#4600000
1%
#4624000
b11101101000110110101000011011010 3
b10100101100101010101110001001011 0
0)
0!
0'
b11101101000110110101000011011010 ,
b10010000000110000100111000100000 $
0&
0"
0-
1(
0+
b10100101100101010101110001001011 *
#4625000
0%
#4650000
1%
#4674000
b10101111010001010101111001011110 3
b111101011111110101101101111010 0
1#
1.
1)
1!
b10101111010001010101111001011110 ,
b10110111000001001110001001101110 $
1&
1"
1-
b111101011111110101101101111010 *
#4675000
0%
#4700000
1%
#4724000
b1101010110011010111001111010101 3
b1001010010111101001100010010 0
0#
0.
0)
0!
1'
b1101010110011010111001111010101 ,
b10100101001101100101110001001010 $
0&
1+
b1001010010111101001100010010 *
#4725000
0%
#4750000
1%
#4774000
b101110000100111000110101011100 3
b1110110011000010101001111101100 0
1#
1.
b101110000100111000110101011100 ,
b10110100001110100011100101101 $
1&
0"
0-
0+
b1110110011000010101001111101100 *
#4775000
0%
#4800000
1%
#4824000
b110010010011001101100001100 3
b1111111110110111011001111111111 0
b110010010011001101100001100 ,
b1001110111111100001100010011 $
1"
1-
b1111111110110111011001111111111 *
#4825000
0%
#4850000
1%
#4874000
b11011110111010011101010010111101 3
b110101010101010111101101101010 0
0'
b11011110111010011101010010111101 ,
b10111001001010111000100101110 $
0"
0-
0(
b110101010101010111101101101010 *
#4875000
0%
#4900000
1%
#4924000
b11100100110110000010000011001001 3
b11000111101101000011101010001111 0
b11100100110110000010000011001001 ,
b11100100100000100100110011001001 $
1(
1+
b11000111101101000011101010001111 *
#4925000
0%
#4950000
1%
#4974000
b11000000010001100111001010000000 3
b1101111110011111111000111011111 0
0#
0.
1'
b11000000010001100111001010000000 ,
b10011110101000110100000100 $
1"
1-
0(
b1101111110011111111000111011111 *
#4975000
0%
#5000000
1%
#5024000
b1101111001101000010010111011110 3
b11101111100011010110010011011111 0
1#
1.
1)
1!
0'
b1101111001101000010010111011110 ,
b1000000010011000010100010000 $
0"
0-
b11101111100011010110010011011111 *
#5025000
0%
#5050000
1%
#5074000
b100111001000000110001101001110 3
b110000110000111000111101100001 0
0)
0!
1'
b100111001000000110001101001110 ,
b10111101111011000011100101111 $
0&
1"
1-
1(
b110000110000111000111101100001 *
#5075000
0%
#5100000
1%
#5124000
b10111010001111000001100101110 3
b11001110000000111110110010011100 0
0#
0.
b10111010001111000001100101110 ,
b1110100100010101011101111101001 $
0(
b11001110000000111110110010011100 *
#5125000
0%
#5150000
1%
#5174000
b1011101100000110110001110111011 3
b11010000000111011111000010100000 0
1)
1!
b1011101100000110110001110111011 ,
b1101000110011010000100111010001 $
1&
0"
0-
b11010000000111011111000010100000 *
#5175000
0%
#5200000
1%
#5224000
b10101110101001101101010001011101 3
b11001111111101010101000010011111 0
1#
1.
b10101110101001101101010001011101 ,
b11101011101100001111011011010111 $
0&
1"
1-
b11001111111101010101000010011111 *
#5225000
0%
#5250000
1%
#5274000
b1000111111010111110111110001111 3
b10100111000000110111010001001110 0
0'
b1000111111010111110111110001111 ,
b11000111110111000001100110001 $
1&
b10100111000000110111010001001110 *
#5275000
0%
#5300000
1%
#5324000
b1101001110011010111011111010011 3
b11001100110111100101100110011 0
0#
0.
0)
0!
b1101001110011010111011111010011 ,
b100100111010010000011101001001 $
0&
0"
0-
b11001100110111100101100110011 *
#5325000
0%
#5350000
1%
#5374000
b1101011000110011111100011010 3
b11100110010110011010100111001 0
b1101011000110011111100011010 ,
b11101001100110110001110011010011 $
1(
b11100110010110011010100111001 *
#5375000
0%
#5400000
1%
